{
    "title": "Corporate Bitcoin Adoption Forges Ahead as More Listed Firms Ride the Wave",
    "time": "2025-01-15T10:05:00",
    "author": "James Van Straten",
    "summary": "In the last few weeks, four firms have announced bitcoin purchases, while seven companies announced a strategy, but no acquisition.",
    "content": "Bitcoin\nBTC\n$103,823.66\nadoption by U.S.-listed public companies continues in full steam.\n\nThe latest purchase comes from NYSE-listed Genius Group (GNS). On Jan. 10, GNS reported increasing its bitcoin holding to $35 million, which was ahead of its scheduled target of $120 million. In the process, it acquired 372 BTC at an average price of $94,047 per bitcoin. The first announcement came on Nov. 12, when it announced its \"Bitcoin-first\" strategy.\n\nOn Tuesday, GNS also reported a rights offering, allowing shareholders to purchase additional shares at discounted prices. If fully subscribed, the rights offering could generate $33 million. GNS founder and CEO Roger Hamilton intends to buy join in the rights offering and buy 500,000 shares.\n\nThe firm is also pursuing loan finances to accumulate bitcoin. Shares of GNS closed 7% higher on Tuesday.\n\nApart from GNS, Nasdaq-listed Ming Shing Group (MSW), a wet trades works service provider, also purchased 500 BTC at an average price of $94,375 per bitcoin. MSW shares were up 43% higher year-to-date.\n\nThe new wave of bitcoin treasury adoption surges ahead with four publicly traded companies announcing bitcoin buys and seven companies announcing a strategy, but no acquisition.\n\nDisclaimer: This article, or parts of it, was generated with assistance from AI tools and reviewed by our editorial team to ensure accuracy and adherence to our standards. For more information, see CoinDeskâ€™s full AI Policy.",
    "url": "https://www.coindesk.com/markets/2025/01/15/corporate-bitcoin-adoption-forges-ahead-as-more-listed-firms-ride-the-wave",
    "llm_analysis": {
        "entities": {
            "persons": [
                "Roger Hamilton"
            ],
            "positions": [
                "founder and CEO"
            ],
            "companies": [
                "Genius Group",
                "GNS",
                "Ming Shing Group",
                "MSW"
            ],
            "organizations": [
                "NYSE",
                "Nasdaq",
                "CoinDesk"
            ]
        },
        "cryptocurrencies": [
            "Bitcoin",
            "BTC"
        ],
        "impact_sentiment": "Bullish",
        "reasoning": "The news describes multiple public companies actively purchasing bitcoin and adopting bitcoin-first strategies, with stock prices rising as a result, indicating growing institutional adoption and market confidence."
    }
}