{
    "title": "U.S. Crypto Task Force to Focus on Delivering National Bitcoin Reserve: Bernstein",
    "time": "2025-02-17T09:34:00",
    "author": "Will Canny",
    "summary": "The Federal Reserve could issue debt or sell some of its gold reserves to fund purchases of BTC, the report said.",
    "content": "The U.S. crypto task force will focus on starting up a national bitcoin\nBTC\n$103,900.89\nreserve, a move that is likely to spur similar efforts worldwide, broker Bernstein said in a research report Monday.\n\n\"A creation of a U.S. bitcoin reserve could lead to a global race amongst sovereigns to buy bitcoin as one of the reserve assets,\" analysts led by Gautam Chhugani wrote.\n\nThe formation of a strategic reserve poses a number of structural questions, the report said.\n\nWill the U.S. Federal Reserve or the Treasury buy bitcoin? If the Fed, that would require legislative approval, the report noted.\n\nHow would the Fed fund cryptocurrency purchases? Bernstein said it could issue debt or sell some of its gold reserves.\n\nThe U.S. government could add the $20 billion in bitcoin it has seized from criminal enterprises to any national reserve, the report added.\n\nThe broker noted that the Trump administration also announced the creation of a sovereign wealth fund (SWF).\n\nSuch a fund \"would consider key U.S. crypto companies/market leaders, as strategic assets to own,\" Bernstein said. \"Investors should position themselves for the next leg of the bull market across bitcoin and bitcoin linked equities.\"\n\nRead more: Crypto Ecosystem Growth Slowed in January Even as Total Market Cap Rose, JPMorgan Says",
    "url": "https://www.coindesk.com/markets/2025/02/17/u-s-crypto-task-force-to-focus-on-delivering-national-bitcoin-reserve-bernstein",
    "llm_analysis": {
        "entities": {
            "persons": [
                "Gautam Chhugani"
            ],
            "positions": [
                "analysts"
            ],
            "companies": [
                "Bernstein",
                "JPMorgan"
            ],
            "organizations": [
                "U.S. crypto task force",
                "Federal Reserve",
                "Treasury",
                "U.S. government",
                "Trump administration"
            ]
        },
        "cryptocurrencies": [
            "Bitcoin",
            "BTC"
        ],
        "impact_sentiment": "Bullish",
        "reasoning": "The report suggests potential U.S. government bitcoin purchases and advises investors to position for 'the next leg of the bull market'."
    }
}