{
    "title": "Crypto for Advisors: Generating Yield With Bitcoin",
    "time": "2025-04-17T15:00:00",
    "author": "Todd Bendell",
    "summary": "Beyond just stacking bitcoin and waiting for price appreciation, BTC-on-BTC yield provides opportunities to grow bitcoin holdings.",
    "content": "In today’s crypto for advisors, Todd Bendell from Amphibian Capital breaks down bitcoin yield products as a strategy to grow bitcoin holdings beyond price appreciation.\n\nThen, Rich Rines, an initial Core DAO developer, provides guidance to Bitcoin developers in Ask an Expert.\n\nExclusive event alert for financial advisors: Join CoinDesk for Wealth Management Day on May 15th at Consensus Toronto. Registered wealth advisors are provided with their own day of networking and learning where they will acquire timely and actionable information about digital assets. Approved advisors receive a complimentary 3-day Platinum Pass ($1,750 value) to Consensus. Apply today.\n\n– Sarah Morton\n\nYou’re reading Crypto for Advisors, CoinDesk’s weekly newsletter that unpacks digital assets for financial advisors. Subscribe here to get it every Thursday.\n\nBitcoin was never meant to sit idle.\n\nFor over a decade, bitcoin has served as a digital store of value, a hedge against monetary debasement and more recently, a core allocation in institutional portfolios. As the asset matures and infrastructure improves, long-term holders are asking a new question: How do I put my bitcoin to work — without leaving the Bitcoin ecosystem?\n\nThe answer lies in a growing but underexplored category of strategies: BTC-on-BTC yield.\n\nLet’s be clear: this isn’t about lending your BTC on unregulated platforms or chasing high annual percentage yields (APYs) à la BlockFi. That playbook collapsed under the weight of counterparty risk and opacity. What’s emerged over the last two years is a more institutional alternative — diversified, risk-managed access to systematic arbitrage and quantitative strategies, all denominated in bitcoin.\n\nWhy BTC-native yield matters\n\nFor most assets, it’s a given that money should work for you. We don’t keep dollars under a mattress or tucked away on a thumb drive — we invest them. Yet in the bitcoin world, the dominant narrative has long been “hold and wait.”\n\nThat mindset made sense when bitcoin was fighting for legitimacy. But in today’s environment — where BTC is being adopted by sovereign wealth funds and traded on major exchanges — long-term holders need better tools.\n\nBTC-on-BTC yield solves this. It aligns with the ethos of accumulating more BTC but does so through institutional-grade strategies that aim to generate returns in BTC, not just on BTC. That distinction matters.\n\nCold storage isn’t a strategy\n\nThere’s also a myth that simply holding bitcoin in cold storage is the safest option. The phrase “not your keys, not your coins” has become dogma — but it deserves a second look.\n\nIn reality, cold storage comes with its own risks: human error, hardware failure, loss of keys and in many cases, an inability to generate any yield whatsoever. Meanwhile, professional custodians — regulated, insured and audited — are now standard infrastructure providers in digital asset management.\n\nFor allocators managing material BTC positions, yield-generating custody isn’t a tradeoff. It’s an upgrade.\n\nHow these strategies work\n\nToday’s BTC-native yield opportunities span a wide range — from delta-neutral basis trades and statistical arbitrage to DeFi yield farming and machine learning-driven quant execution — but all settled in BTC.\n\nReturns are calculated and distributed in kind. The objective is simple: accumulate more BTC over time, without needing to rely solely on price appreciation.\n\nBy allocating across a diversified mix of strategies and managers, investors can pursue consistent BTC growth while mitigating single-strategy or single-manager risk.\n\nWhy BTC-on BTC yield is timely\n\nSeveral forces are converging right now:\n\nIn short, bitcoin is growing up. The question is whether the strategies around it will grow with it.\n\nRethinking HODLing\n\nBTC-on-BTC yield and long-term holding aren’t mutually exclusive. Allocators can continue to hold core BTC positions while using active strategies to pursue steady accumulation.\n\nThat requires moving beyond cold storage maxims and exploring yield strategies that reflect the sophistication of today’s markets. With proper risk controls, BTC-native yield offers a pragmatic path to accumulate more BTC without abandoning its core principles.\n\nThe bottom line is that bitcoin doesn’t have to sit on the sidelines. It can move with the market — and grow with it.\n\nFor allocators thinking in decades, BTC-on-BTC yield opens the door to a more productive bitcoin strategy — one that matches conviction with action.\n\n- Todd Bendell, Managing General Partner, Amphibian Capital\n\nQ. What’s the best way to align early developer incentives with long-term protocol value?\n\nA. The key is to reward real product-market fit and real users — not short-term speculation. That starts with building tight relationships and solving problems for real communities. From there, it's about fostering an “eat what you kill” ecosystem, in which builders who ship products people actually use are rewarded with real economic upside — not just points, grants or temporary incentives. When developers are compensated based on the value they create for users, long-term alignment takes care of itself.\n\nQ. When just starting out in crypto, how can developers filter for signal over noise?\n\nA. Don’t just chase the hot thing — look for what will still matter in 5 to 10 years. That’s one of the key reasons Bitcoin remains a compelling foundation for builders. It has dedicated users, immense value and a clear product-market fit. Developers should focus on real usage and demand instead of short-term token price action. If you're building something that keeps people engaged because it's useful — not because it's yield-farming season — you’re already filtering signal from noise.\n\nQ. What lessons from Bitcoin’s design philosophy are still underutilized?\n\nA. Bitcoin is dominant not because it does the most, but because it does one thing better than anyone else. Its product-market fit as digital gold is crypto’s most proven use case — and yet it’s still underrated. Too many forget that simplicity with real utility wins. Building around Bitcoin and extending its utility without compromising its foundation remains one of the most underrated opportunities in the space today.\n\n- Rich Rines, an initial contributor, Core DAO",
    "url": "https://www.coindesk.com/coindesk-indices/2025/04/16/crypto-for-advisors-generating-yield-with-bitcoin",
    "llm_analysis": {
        "entities": {
            "persons": [
                "Todd Bendell",
                "Rich Rines",
                "Sarah Morton"
            ],
            "positions": [
                "Managing General Partner",
                "initial Core DAO developer",
                "initial contributor"
            ],
            "companies": [
                "Amphibian Capital",
                "CoinDesk",
                "BlockFi"
            ],
            "organizations": [
                "Core DAO"
            ]
        },
        "cryptocurrencies": [
            "Bitcoin",
            "BTC"
        ],
        "impact_sentiment": "Bullish",
        "reasoning": "The article promotes institutional-grade BTC yield strategies as a way to grow bitcoin holdings beyond price appreciation, indicating market maturation and increased utility that could drive adoption and confidence."
    }
}