{
    "title": "Crypto Daybook Americas: Bitcoin ETFs See $275M Buyers, 'Exhausting' Bears, Ahead of FOMC",
    "time": "2025-03-18T11:15:00",
    "author": "Omkar Godbole",
    "summary": "Your day-ahead look for March 18, 2025",
    "content": "By Omkar Godbole (All times ET unless indicated otherwise)\n\nBitcoin\nBTC\n$104,850.17\ntraded around its 200-day average of $84,000 as the notorious Hyperliquid whale exited its multimillion dollar short BTC position. Smaller coins like CAKE, TKX, OKB and ATOM contributed to market optimism with positive performances.\n\nThe SUI token struggled to extend Monday's 6% surge, which was spurred by asset managers' ETF filings with the SEC, showcasing growing institutional interest in the wider crypto market.\n\nWhile some analysts declared the end of the bitcoin bull run, casting doubt about the sustainability of the recent bounce, data indicated otherwise, pointing to exhaustion in the ETF-led selling pressure.\n\nOn Monday, U.S.-based spot bitcoin ETFs attracted $275 million in investor funds, building on Friday's $41 million influx. That's the first back-to-back inflows since Feb. 7, according to data tracked by Farside Investors.\n\n\"This data reinforces the narrative that ETF-driven selling pressure is exhausting,\" said Valentin Fournier, an analyst at BRN. \"If this trend continues, we could see inflows gradually build momentum, further supporting bitcoinâ€™s price.\"\n\nThe Fed's rate decision on Wednesday could introduce volatility into the crypto market with a dovish statement possibly spurring increased risk-taking.\n\n\"Post-FOMC, bitcoin is expected to trade within the range of $80,000 to $86,000 with 80% confidence, while ethereum is projected to fluctuate between $1,800 and $2,100 under the same confidence level,\" according to Ryan Lee, chief analyst at Bitget Research. \"These ranges reflect potential movements tied to macroeconomic signals, investor sentiment, and broader financial conditions.\"\n\nIn traditional markets, European stocks edged higher before a German parliamentary vote on historic debt reforms. Gold remained firm above $3,000 per ounce, with BlackRock calling the yellow metal a better diversifier than Treasury notes in the ongoing macro environment.\n\nMeanwhile, futures tied to the Nasdaq, S&P 500 and Dow traded unchanged to negative amid reports that the Trump-Putin call regarding the Ukraine peace deal would take place between 13:00 and 15:00 GMT. Stay alert!\n\nBy Shaurya Malwa\n\nSpot BTC ETFs:\n\nSpot ETH ETFs\n\nSource: Farside Investors",
    "url": "https://www.coindesk.com/daybook-us/2025/03/18/crypto-daybook-americas-cake-tkx-add-spark-as-bitcoin-treads-water-before-fed",
    "llm_analysis": {
        "entities": {
            "persons": [
                "Omkar Godbole",
                "Valentin Fournier",
                "Ryan Lee",
                "Shaurya Malwa"
            ],
            "positions": [
                "analyst",
                "chief analyst"
            ],
            "companies": [
                "BRN",
                "Bitget Research",
                "BlackRock"
            ],
            "organizations": [
                "SEC",
                "Farside Investors",
                "Fed",
                "FOMC"
            ]
        },
        "cryptocurrencies": [
            "Bitcoin",
            "BTC",
            "CAKE",
            "TKX",
            "OKB",
            "ATOM",
            "SUI",
            "Ethereum",
            "ETH"
        ],
        "impact_sentiment": "Bullish",
        "reasoning": "The news highlights $275 million in bitcoin ETF inflows, exhaustion of selling pressure, positive performances from smaller coins, and growing institutional interest, all indicating market optimism."
    }
}