{
    "title": "Trump-Affiliated World Liberty Financial Makes Another TRX Buy",
    "time": "2025-01-22T05:45:00",
    "author": "Sam Reynolds",
    "summary": "The most recent purchase brings WLFI's TRX holdings to $7.5 million.",
    "content": "World Liberty Financial Financial (WLFI), the crypto project backed by the family of U.S. President Donald Trump, has made another purchase of Tron's TRX for its treasury on-chain data shows.\n\n“As a strong advocate for blockchain technology and innovation in cryptocurrencies, I'm excited to see World Liberty Financial integrate TRON as a key part of its growing treasury. TRX's inclusion as the fourth-largest asset in WLFI's holdings highlights its trust in the Tron blockchain network,\" Justin Sun, founder of Tron, said in a statement to CoinDesk.\"\n\nThis most recent purchase was to the tune of $2.6 million and adds an additional 10.8 million TRX to the WLFI treasury. The total holdings of TRX now come in at $7.5 million.\n\n\"With WLFI leading efforts to bridge traditional finance and crypto and the Trump administration's pro-crypto stance, the United States will become a major hub for innovation and cryptocurrency adoption,” Sun continued.\n\nCoinDesk reported in mid-January that WFLI intended to purchase TRX and a Tron delegation attended Trump's inauguration.\n\nWFLI is also holding $182 million in ETH, $48 million in WBTC, $7.2 million in Tether's USDT, $7 million in AAVE, and $6.7 million in Chainlink's LINK according to on-chain data with most token buys coming in before the inauguration.\n\nSources close to the matter say WLFI will continue to increase their TRX holdings.",
    "url": "https://www.coindesk.com/markets/2025/01/22/trump-affiliated-world-liberty-financial-makes-another-trx-buy",
    "llm_analysis": {
        "entities": {
            "persons": [
                "Donald Trump",
                "Justin Sun"
            ],
            "positions": [
                "U.S. President",
                "founder of Tron"
            ],
            "companies": [
                "World Liberty Financial",
                "CoinDesk",
                "Tether",
                "Chainlink"
            ],
            "organizations": [
                "Trump administration",
                "Tron blockchain network"
            ]
        },
        "cryptocurrencies": [
            "TRX",
            "ETH",
            "WBTC",
            "USDT",
            "AAVE",
            "LINK"
        ],
        "impact_sentiment": "Bullish",
        "reasoning": "The news describes significant institutional buying of TRX and other cryptocurrencies by a Trump-affiliated company, with positive statements about blockchain innovation and US cryptocurrency adoption."
    }
}