{
    "title": "Bitcoin Rally Reverses Despite Supposedly Bullish GameStop News",
    "time": "2025-03-26T16:19:00",
    "author": "Krisztian Sandor",
    "summary": "At least one analyst questioned why GameStop's plan to buy bitcoin was necessarily a good thing.",
    "content": "Bitcoin's\nBTC\n$104,116.60\nrise following GameStop's Tuesday bitcoin treasury strategy announcement halted just shy of the $89,000 level and things are now headed decidedly lower during U.S. trading hours Wednesday.\n\nJust after the noon hour on the east coast, bitcoin has pulled back about 3% from overnight highs to $86,500. The broad-market crypto benchmark CoinDesk 20 Index was 1.9% lower through the past 24 hours, with ether\nETH\n$3,510.13\n, solana\nSOL\n$161.70\nand AAVE declining around 3%-4% during the same period.\n\nThe price action happened with U.S. risk assets showing weakness. The S&P500 and Nasdaq indexes were down 0.8% and 1.6%, respectively, erasing most of their gains since Monday's opening.\n\nFresh concerns over the U.S. debt ceiling perhaps loomed over markets. The Congressional Budget Office issued a warning today that the federal government may run out of money as soon as August if lawmakers don't raise the debt limit. U.S. tariffs, poised to go into effect on April 2, could also be weighing on investor nerves.\n\n\"Uncertainty surrounding U.S. trade policy and the broader political landscape remains front of mind,\" analysts at hedge fund QCP said in a Telegram broadcast. \"The market still lacks clarity on the scope, timing and magnitude of these potential actions. Until then, we expect more sideways volatility.\"\n\nBitcoin bulls, meanwhile, are once again left scratching their heads as the price fails to react positively to news of yet another deep-pocketed buyer planning to invest in the world's largest crypto.\n\n\"Zombie companies like GameStop 'pulling a Saylor' as a get out of jail cared would be a clear topping signal,\" said James Check, first one year ago and then again Tuesday evening following GME's announcement.\n\nHe reminded that he said similar about publicly trader miners when those capital-burning companies decided to stack bitcoin beyond what their mining activity provided.\n\n\"Three months ago I couldn't make a case for where this cycle's excess sell-side comes like we saw in the 2022 bear market ... I suspect in a few months time, I will be able to make a case once again.\"",
    "url": "https://www.coindesk.com/markets/2025/03/26/bitcoin-rally-stalls-despite-supposedly-bullish-gamestop-news",
    "llm_analysis": {
        "entities": {
            "persons": [
                "James Check"
            ],
            "positions": [
                "analyst",
                "analysts"
            ],
            "companies": [
                "GameStop",
                "GME"
            ],
            "organizations": [
                "Congressional Budget Office",
                "QCP"
            ]
        },
        "cryptocurrencies": [
            "Bitcoin",
            "BTC",
            "ether",
            "ETH",
            "solana",
            "SOL",
            "AAVE"
        ],
        "impact_sentiment": "Bearish",
        "reasoning": "Bitcoin's rally reversed with a 3% pullback and broader crypto market declines of 1.9-4%, accompanied by analyst skepticism about GameStop's bitcoin strategy and broader market uncertainty."
    }
}