{
    "title": "US SEC Closes Investigation Into Robinhood's Crypto Business",
    "summary": "On Feb 21. the SEC’s Enforcement Division said it had concluded its investigation, Robinhood said in a statement.",
    "time": "2025-02-24T14:49:00",
    "author": "Camomile Shumba",
    "content": "The U.S. Securities and Exchange Commission has closed its investigation into Robinhood's crypto business, the trading platform said in a statement on Monday.\n\n\"On February 21, 2025, the SEC’s Enforcement Division advised RHC in a letter that it had concluded its investigation and did not intend to move forward with an enforcement action,\" the company said.\n\nThe company received a Wells notice from the SEC indicating that it would recommend pursuing an enforcement action in May. A Wells notice is a formal announcement from the regulator saying it believes it has evidence that the recipient — Robinhood, in this case — broke the law.\n\n\"As we explained to the SEC, any case against Robinhood Crypto would have failed. We appreciate the formal closing of this investigation, and we are happy to see a return to the rule of law and commitment to fairness at the SEC,” said Dan Gallagher, Robinhood's chief legal, compliance and corporate affairs officer, in a statement.\n\nThe SEC is also poised to drop its case against crypto exchange Coinbase and has dropped its investigation into non-fungible token platform OpenSea.\n\nAn SEC spokesperson declined to comment.\n\nThe U.S. Securities and Exchange Commission has closed its investigation into Robinhood's crypto business, the trading platform said in a statement on Monday.\n\n\"On February 21, 2025, the SEC’s Enforcement Division advised RHC in a letter that it had concluded its investigation and did not intend to move forward with an enforcement action,\" the company said.\n\nThe company received a Wells notice from the SEC indicating that it would recommend pursuing an enforcement action in May. A Wells notice is a formal announcement from the regulator saying it believes it has evidence that the recipient — Robinhood, in this case — broke the law.\n\n\"As we explained to the SEC, any case against Robinhood Crypto would have failed. We appreciate the formal closing of this investigation, and we are happy to see a return to the rule of law and commitment to fairness at the SEC,” said Dan Gallagher, Robinhood's chief legal, compliance and corporate affairs officer, in a statement.\n\nThe SEC is also poised to drop its case against crypto exchange Coinbase and has dropped its investigation into non-fungible token platform OpenSea.\n\nAn SEC spokesperson declined to comment.\n\nMore For You\n\nInside Zcash: Encrypted Money at Planetary Scale\n\nA deep dive into Zcash's zero-knowledge architecture, shielded transaction growth, and its path to becoming encrypted Bitcoin at scale.\n\nWhat to know:\n\nIn 2025, Zcash evolved from niche privacy tech into a functioning encrypted-money network:\n\nIn 2025, Zcash evolved from niche privacy tech into a functioning encrypted-money network:\n\nAppeals Court Seems Unmoved by Sam Bankman-Fried’s Claims of an Unfair Trial\n\nThe former FTX CEO, who is currently serving a 25-year sentence for fraud, has repeatedly claimed that the crypto exchange was solvent at the time of its bankruptcy.\n\nWhat to know:",
    "url": "https://www.coindesk.com/policy/2025/02/24/us-sec-closes-investigation-into-robinhood-s-crypto-business",
    "llm_analysis": {
        "entities": {
            "persons": [
                "Dan Gallagher"
            ],
            "positions": [
                "chief legal, compliance and corporate affairs officer"
            ],
            "companies": [
                "Robinhood",
                "Robinhood Crypto",
                "Coinbase",
                "OpenSea",
                "FTX"
            ],
            "organizations": [
                "U.S. Securities and Exchange Commission",
                "SEC",
                "SEC’s Enforcement Division",
                "Appeals Court"
            ]
        },
        "cryptocurrencies": [
            "Bitcoin",
            "Zcash"
        ],
        "impact_sentiment": "Bullish",
        "reasoning": "The SEC closing investigations into Robinhood's crypto business and dropping cases against Coinbase and OpenSea indicates reduced regulatory pressure, which typically boosts market confidence."
    }
}