{
    "title": "Northern Trust to Provide Custody, Cash Management Services for Stablecoin Issuer Haycen",
    "time": "2025-03-27T08:59:00",
    "author": "Will Canny",
    "summary": "Haycen provides stablecoin-based solutions for non-bank lenders in global trade.",
    "content": "TradFi giant Northern Trust (NTRS) will provide custody and cash management services for trade finance focused stablecoin issuer Haycen, the company said in a press release Thursday.\n\nNorthern Trust Asset Servicing will be responsible for providing Haycen with global custody services for its client fiat deposits, and Northern Trust Asset Management will provide cash sweep services, the company said.\n\nStablecoins are cryptocurrencies whose value is tied to another asset, such as the U.S. dollar or gold. They play a major role in cryptocurrency markets and are also used to transfer money internationally.\n\nHaycen is a trade finance digital payments provider, with operations in the U.K. and Europe. The company offers wholesale stablecoin-based solutions for non-bank lenders in global trade.\n\nTrade finance is a vital part of global commerce that is ripe for modernization. The industry is still reliant on manual workflows and can be expensive for banks and companies involved.\n\nAccess is also an issue. Smaller sized businesses are prevented from accessing trade finance due to the costs and complexity of the existing system. This is where stablecoins can help.\n\nHaycen offers increased availability to U.S. dollars via stablecoins, combined with instant settlement, thereby reducing the traditional friction associated with cross-border transfers.\n\n\"Global trade is an incredibly important part of the economy and a fantastic\nmarket for us as a stablecoin solution; the global flow of goods and services\nrelies on liquidity moving unencumbered and successive regulatory changes\nhave forced banks to scale back trade lending operations,\" said Luke Sully, founder and CEO of Haycen, in emailed comments.\n\n\"Thatâ€™s left a gap in the market for non-bank players looking for new ways to\nmove the $2 trillion of annual flows, 95% of which is denominated in USD,\" Sully said, adding that \"for these participants, using stablecoins combines yield enhancement with the certainty of instant free global settlement.\"\n\nHaycen has received funding from the U.K. government to develop institutional-grade stablecoins.\n\nThese cryptocurrencies have been grabbing headlines this week.\n\nFidelity Investments is in advanced stages of developing its own stablecoin, the Financial Times reported on Wednesday.\n\nWLFI\n$0.1276\n, a decentralized finance protocol backed by U.S. President Trump, also confirmed its own plans to launch a stablecoin.\n\nRead more: Trump-Backed World Liberty Financial Confirms Dollar Stablecoin Plans With BitGo",
    "url": "https://www.coindesk.com/business/2025/03/26/northern-trust-to-provide-custody-and-cash-management-services-for-stablecoin-issuer-haycen",
    "llm_analysis": {
        "entities": {
            "persons": [
                "Luke Sully"
            ],
            "positions": [
                "founder and CEO"
            ],
            "companies": [
                "Northern Trust",
                "Haycen",
                "Fidelity Investments",
                "WLFI",
                "World Liberty Financial",
                "BitGo"
            ],
            "organizations": [
                "U.K. government",
                "Financial Times"
            ]
        },
        "cryptocurrencies": [
            "stablecoin"
        ],
        "impact_sentiment": "Bullish",
        "reasoning": "The news describes major traditional financial institutions entering the stablecoin space and providing institutional-grade services, indicating growing mainstream adoption and confidence in cryptocurrency markets."
    }
}