{
    "title": "Robinhood CEO Warns Lack of U.S. Regulation Stifles Security Tokenization Efforts",
    "time": "2025-01-29T18:33:00",
    "author": "Krisztian Sandor",
    "summary": "Vlad Tenev joined BlackRock CEO Larry Fink in calling for clear regulations for tokenized securities in the U.S.",
    "content": "Current U.S. regulations are blocking a major financial shift that could open up private-market investments to everyday investors through tokenization, CEO of digital brokerage Robinhood Vlad Tenev said.\n\nIn a Wednesday opinion piece for the Washington Post, Tenev said that many high-growth companies like OpenAI, SpaceX and Stripe are increasingly avoiding going public, limiting investment access to a small circle of wealthy investors, widening the investment gap between retail investors.\n\nTokenizing private equity through blockchain technology that underpins crypto markets would allow retail to access companies early in their growth phase, lowering barriers while keeping proper disclosures and investor protections, Tenev argued.\n\n\"The world is tokenizing, and the United States should not get left behind,\" Tenev wrote. \"Itâ€™s time to update our conversation about crypto from bitcoin and meme coins to what blockchain is really making possible: A new era of ultra-inclusive and customizable investing fit for this century.\"\n\nHowever, U.S. regulators, particularly the Securities and Exchange Commission (SEC), have yet to provide a clear framework and rules for registering security tokens, while other key markets such as the EU, Singapore and Abu Dhabi are already advancing in this area, he said.\n\nHe proposed creating a security token registration framework as an alternative to IPOs, providing clear guidelines for exchanges and broker-dealers to support tokenized assets and updating accredited investor rules to allow access based on financial knowledge instead of wealth.\n\nTokenization is a booming sector at the intersection of crypto and traditional finance that could become a multitrillion-dollar market this decade, per forecasts by McKinsey, BCG, 21Shares and Bernstein . Institutions and even governments are increasingly exploring placing real-world assets like bonds, funds and commodities and real estate on blockchain rails in a digital token form to achieve speedier settlements and broader investor accessibility.\n\nTenev is the latest high-profile leader in the financial world touting tokenization and calling for clear rules for tokenized securities. Larry Fink, CEO of $10 trillion asset manager BlackRock, recently said that tokenization is the next frontier that will change markets, and urged the SEC in a CNBC interview to \"rapidly approve\" tokenization of stocks and bonds.",
    "url": "https://www.coindesk.com/business/2025/01/29/robinhood-ceo-warns-lack-of-u-s-regulation-stifles-security-tokenization-efforts",
    "llm_analysis": {
        "entities": {
            "persons": [
                "Vlad Tenev",
                "Larry Fink"
            ],
            "positions": [
                "CEO",
                "CEO of digital brokerage Robinhood",
                "CEO of $10 trillion asset manager BlackRock"
            ],
            "companies": [
                "Robinhood",
                "OpenAI",
                "SpaceX",
                "Stripe",
                "BlackRock",
                "McKinsey",
                "BCG",
                "21Shares",
                "Bernstein"
            ],
            "organizations": [
                "Washington Post",
                "Securities and Exchange Commission",
                "SEC",
                "EU"
            ]
        },
        "cryptocurrencies": [
            "bitcoin"
        ],
        "impact_sentiment": "Bullish",
        "reasoning": "The news highlights major financial leaders calling for regulatory clarity to enable tokenization, which is described as a multitrillion-dollar opportunity that would expand blockchain adoption beyond cryptocurrencies."
    }
}