{
    "title": "Crypto Daybook Americas: Bitcoin Bulls Play 'Heads I Win, Tails Bears Loseâ€™ as BTC Tops $94K",
    "time": "2025-04-23T11:15:00",
    "author": "Omkar Godbole",
    "summary": "Your day-ahead look for April 23, 2025",
    "content": "By Omkar Godbole (All times ET unless indicated otherwise)\n\nFor bitcoin bulls, it's a case of \"heads I win, tails you lose.\"\n\nIt's risk-on-time and boding well for BTC, which rose above $94,000 to mark a more than 50% retracement of the sell-off from record highs above $109,000 to $74,000.\n\nThe cryptocurrency has experienced a sharp rally in the past 24 hours, coinciding with President Donald Trump saying he does not intend to fire Fed Chair Jerome Powell and making conciliatory remarks on trade tensions with China.\n\nBut BTC rose on Monday too. That was supposedly on haven demand as traders sold the dollar, U.S. stocks and bonds on the perceived threat to the Fed's independence.\n\nNo wonder some analysts say the largest cryptocurrency is simultaneously a risk play due to its emerging tech appeal and a haven akin to digital gold.\n\nThe latest surge also boosted morale in the wider crypto market. SUI, BONK, ENA, NEAR and AGLO have climbed more than 20% in just 24 hours. IMX surged over 40%, while ether\nETH\n$3,515.90\n, the biggest altcoin, is trading about 10% higher. Bitcoin's dominance rate dropped slightly, indicating a traders' renewed willingness to take on risk.\n\nIn traditional markets, traders are covering their USD short positions, with some taking outright bullish bets on the dollar. This shift comes amid a decline in gold prices and a positive upswing on Wall Street.\n\nSupporting the case for a continued move higher in BTC is the renewed optimism about institutional adoption. The FT reported that Brandon Lutnick, son of U.S. Commerce Secretary Howard Lutnick, is working with SoftBank, Tether and Bitfinex to capitalize on the crypto revival under the Trump administration.\n\n\"The $3 billion fund plans to raise an additional $350 million via convertible bonds, alongside a $200 million private equity round, with one clear directive: buy more Bitcoin, and buy it big,\" according to Singapore-based QCP Capital.\n\nThe announcement comes on the heels of decisive shift in the U.S. regulatory policy. On Tuesday, the newly appointed SEC Chairman Paul Atkins reiterated that his top priority is establishing a clear regulatory framework for digital assets.\n\nElsewhere, DeFi Development Corp. deepened its SOL bet with a $11.5 million token purchase. A crypto whale accumulated ether, withdrawing $21.78 million worth of tokens from Binance. Stay alert!\n\nCoinDesk's Consensus is taking place in Toronto on May 14-16. Use code DAYBOOK and save 15% on passes.\n\nBy Shaurya Malwa\n\nSpot BTC ETFs:\n\nSpot ETH ETFs\n\nSource: Farside Investors",
    "url": "https://www.coindesk.com/daybook-us/2025/04/23/crypto-daybook-americas-bitcoin-bulls-play-heads-i-win-tails-bears-lose-as-btc-tops-usd94k",
    "llm_analysis": {
        "entities": {
            "persons": [
                "Omkar Godbole",
                "Donald Trump",
                "Jerome Powell",
                "Brandon Lutnick",
                "Howard Lutnick",
                "Paul Atkins",
                "Shaurya Malwa"
            ],
            "positions": [
                "President",
                "Fed Chair",
                "U.S. Commerce Secretary",
                "SEC Chairman"
            ],
            "companies": [
                "SoftBank",
                "Tether",
                "Bitfinex",
                "QCP Capital",
                "DeFi Development Corp.",
                "Binance",
                "CoinDesk",
                "Farside Investors"
            ],
            "organizations": [
                "Fed",
                "SEC"
            ]
        },
        "cryptocurrencies": [
            "Bitcoin",
            "BTC",
            "SUI",
            "BONK",
            "ENA",
            "NEAR",
            "AGLO",
            "IMX",
            "ether",
            "ETH",
            "SOL"
        ],
        "impact_sentiment": "Bullish",
        "reasoning": "The news describes Bitcoin rising above $94,000 with a sharp rally, institutional adoption optimism, positive regulatory developments, and widespread altcoin gains of 20-40%."
    }
}