{
    "title": "BlockFills and CoinDesk Indices Launch Options Market for CoinDesk 20 Index",
    "time": "2025-01-30T12:00:00",
    "author": "Omkar Godbole",
    "summary": "The CoinDesk 20 Index gets an options market that will bring institutional liquidity to the index.",
    "content": "Institution-focused digital asset technology and trading firm BlockFills is collaborating with CoinDesk Indices to launch options tied to the CoinDesk 20 Index (CD20).\n\nThe CoinDesk 20 Index, which debuted a year ago, measures the performance of leading digital assets, catering to institutional demand for diverse tradable products beyond bitcoin\nBTC\n$103,993.55\nand ether\nETH\n$3,500.73\n. The availability of options means traders can speculate on volatility and time in addition to price direction, bringing professional liquidity to the index.\n\nOptions are derivative contracts that give the holder the right to buy or sell the underlying asset at a predetermined price on or before a specific date. The ongoing crypto bull run, led by the institutionalization of bitcoin, has seen investors embrace options tied to BTC and crypto-linked products, including alternative investment vehicles like spot ETFs.\n\n\"As the digital assets market continues to mature, qualified institutional market participants are demanding a foundational reference index to trade, invest and measure performance,‚Äù said Perry Parker, head of options trading at BlockFills.\n\nInstitutions are already participating in BlockFills's CD20 options, with digital asset manager and multi-strategy crypto fund Hyperion Decimus executing the first transaction this month.\n\nThis also marks the first OTC options trade on a digital asset index with an onshore counterparty (Hyperion) in the U.S., making this a significant milestone in the OTC derivatives market due to extra regulatory oversight in such domestic transactions.\n\n\"The BlockFills CoinDesk 20 index options market is a unique solution for professionals managing a portfolio within this asset class, and we are thrilled to kick off trading of the product,\" said Chris Sullivan, Principal at Hyperion Decimus.\n\n\"Prior to the CoinDesk 20, there was no agreed upon, liquid and diversified benchmark, which answers in part why an index option has not been traded until now,\" Sullivan added.\n\nUPDATE (Jan. 30, 15:21 UTC): Adds additional context about the first OTC options trade in the U.S. and comments from Chris Sullivan.",
    "url": "https://www.coindesk.com/markets/2025/01/30/blockfills-and-coindesk-indices-launch-options-market-for-coindesk-20-index",
    "llm_analysis": {
        "entities": {
            "persons": [
                "Perry Parker",
                "Chris Sullivan"
            ],
            "positions": [
                "head of options trading at BlockFills",
                "Principal at Hyperion Decimus"
            ],
            "companies": [
                "BlockFills",
                "Hyperion Decimus"
            ],
            "organizations": [
                "CoinDesk Indices",
                "CoinDesk 20 Index"
            ]
        },
        "cryptocurrencies": [
            "bitcoin",
            "BTC",
            "ether",
            "ETH"
        ],
        "impact_sentiment": "Bullish",
        "reasoning": "The launch of institutional options for the CoinDesk 20 Index brings professional liquidity and institutional participation to the crypto market during an ongoing bull run."
    }
}