{
    "title": "Innovation Amid Yield Compression: DeFi Lending Markets in Q1 2025",
    "time": "2025-03-31T18:43:00",
    "author": "Ryan Rodenbaugh",
    "summary": "While yields across major lending platforms have compressed significantly, innovation at the market's edges demonstrates DeFi's continued maturation and growth, says Ryan Rodenbaugh, CEO of Wallfacer Labs, the team behind vaults.fyi.",
    "content": "The first quarter of 2025 tells a clear story about DeFi's evolution. While yields across major lending platforms have compressed significantly, innovation at the market's edges demonstrates DeFi's continued maturation and growth.\n\nDeFi yields have declined sharply across all major lending platforms:\n\nThis compression signals a market that’s cooled significantly from late-2024's exuberance, with subdued borrower demand across major platforms.\n\nDespite falling yields, major stablecoin vaults have experienced extraordinary growth:\n\nAs yields have fallen from nearly 15% to under 5%, capital has remained sticky. This seemingly contradictory behavior reflects increasing institutional comfort with DeFi protocols as legitimate financial infrastructure rather than speculative vehicles.\n\nThe emergence of curation represents a significant shift in DeFi lending. Protocols like Morpho and Euler have introduced curators who build, manage, and optimize lending vaults.\n\nThese curators serve as a new breed of DeFi asset managers, evaluating markets, setting risk parameters, and optimizing capital allocations to deliver enhanced yields. Unlike traditional service providers who merely advise protocols, curators actively manage capital deployment strategies across various lending opportunities.\n\nOn platforms like Morpho and Euler, curators handle risk management functions: selecting which assets can serve as collateral, setting appropriate loan-to-value ratios, choosing oracle price feeds, and implementing supply caps. They essentially build targeted lending strategies optimized for specific risk-reward profiles, sitting between passive lenders and sources of yield.\n\nFirms like Gauntlet, previously service providers to protocols like Aave or Compound, now directly manage nearly $750 million in TVL across several protocols. With performance fees ranging from 0-15%, this potentially represents millions in annual revenue with significantly more upside than traditional service arrangements. Per a Morpho dashboard, curators have cumulatively generated nearly 3 million in revenue and based on Q1 revenue are on track to do 7.8mm in 2025.\n\nThe most successful curator strategies have maintained higher yields primarily by accepting higher-yielding collaterals at more aggressive LTV ratios, particularly leveraging Pendle LP tokens. This approach requires sophisticated risk management but delivers superior returns in the current compressed environment.\n\nAs concrete examples, yields on the largest USDC vaults on both Morpho and Euler have outperformed the vaults.fyi benchmark, showing 5-8% base yields and 6-12% yields inclusive of token rewards.\n\nThe compressed environment has created a distinct market structure:\n\nThis two-tier relationship creates a more dynamic market where strategy providers can rapidly iterate on yield opportunities without building core infrastructure. The yields ultimately available to users depend on both the efficiency of the base protocol and the sophistication of strategies deployed on top.\n\nThis restructured market means users now navigate a more complex landscape where the relationship between protocols and strategies determines yield potential. While blue-chip protocols offer simplicity and safety, the combination of optimizing protocols and specialized strategies provides yields comparable to what previously existed on platforms like Aave or Compound during higher rate environments.\n\nDespite the proliferation of L2s and alternative L1s, Ethereum mainnet continues to host many of the top yield opportunities, both inclusive and exclusive of token incentives. This persistence of Ethereum's yield advantage is notable in a market where incentive programs have often shifted yield-seeking capital to newer chains.\n\nAmong mature chains (Ethereum, Arbitrum, Base, Polygon, Optimism), yields remain depressed across the board. Outside of mainnet, most of the attractive yield opportunities are concentrated on Base, suggesting its emerging role as a secondary yield hub.\n\nNewer chains with substantial incentive programs (like Berachain and Sonic) show elevated yields, but the sustainability of these rates remains questionable as incentives eventually taper.\n\nA significant development this quarter was Coinbase's introduction of Bitcoin-collateralized loans powered by Morpho on its Base network. This integration represents the emerging \"DeFi Mullet\" thesis - fintech interfaces in the front, DeFi infrastructure in the back.\n\nAs Coinbase's head of Consumer Products Max Branzburg has noted: \"This is a moment where we're planting a flag that Coinbase is coming on-chain, and we're bringing millions of users with their billions of dollars.\" The integration brings Morpho's lending capabilities directly into Coinbase's user interface, allowing users to borrow up to $100,000 in USDC against their bitcoin holdings.\n\nThis approach embodies the view that billions will eventually use Ethereum and DeFi protocols without knowing it — just as they use TCP/IP today without awareness. Traditional FinTech companies will increasingly adopt this strategy, keeping familiar interfaces while leveraging DeFi's infrastructure.\n\nThe Coinbase implementation is particularly notable for its full-circle integration within the Coinbase ecosystem: users post BTC collateral to mint cbBTC (Coinbase's wrapped Bitcoin on Base) and borrow USDC (Coinbase's stablecoin) on Morpho (a Coinbase-funded lending platform) atop Base (Coinbase's Layer 2 network).\n\nSeveral factors could reshape the lending landscape through 2025:\n\nThe protocols best positioned to thrive will be those that can operate efficiently across the risk spectrum, serving both conservative institutional capital and more aggressive yield-seekers, through increasingly sophisticated risk management and capital optimization strategies.",
    "url": "https://www.coindesk.com/markets/2025/03/31/innovation-amid-yield-compression-defi-lending-markets-in-q1-2025",
    "llm_analysis": {
        "entities": {
            "persons": [
                "Ryan Rodenbaugh",
                "Max Branzburg"
            ],
            "positions": [
                "CEO",
                "head of Consumer Products"
            ],
            "companies": [
                "Wallfacer Labs",
                "Gauntlet",
                "Coinbase"
            ],
            "organizations": [
                "Morpho",
                "Euler",
                "Aave",
                "Compound"
            ]
        },
        "cryptocurrencies": [
            "Bitcoin",
            "BTC",
            "Ethereum",
            "USDC",
            "cbBTC"
        ],
        "impact_sentiment": "Bullish",
        "reasoning": "The news highlights DeFi's maturation with institutional comfort, significant growth in stablecoin vaults despite yield compression, and major integrations like Coinbase bringing millions of users on-chain."
    }
}