{
    "title": "Crypto Daybook Americas: Litecoin Leads on Optimistic ETF Signal as Market Rallies After Powell Talks",
    "time": "2025-01-30T12:00:00",
    "author": "Omkar Godbole",
    "summary": "Your day-ahead look for Jan. 30, 2025",
    "content": "By Omkar Godbole (All times ET unless indicated otherwise)\n\nThe crypto market is trading positively with the Fed risk event out of the way, focusing on positives such as the crypto-friendly president in the White House, the renewed upswing in Tether's market, and the bullish Chinese New Year effect.\n\nAmong cryptocurrencies with $5 billion-plus market valuations, the standout performer is\nLTC\n$86.67\n, the silver to bitcoin's gold, which has jumped more than 11% since the early Asian hours compared with gains of 1% to 3% for the rest. It is the third-best performing of the top 100 coins in the past 24 hours, thanks to the SEC acknowledging Canary Capitalâ€™s Litecoin ETF proposal. That has opened for public feedback, a move that hints at potential approval in the coming months.\n\n\"This is the first altcoin ETF filing to get acknowledged,\" Bloomberg Senior ETF analyst Eric Balchunas said on X, noting that the proposal is the one to make the most progress in regulatory requirements.\n\nA potential listing could be as positive for LTC as it has been for BTC and ETH. Note that despite the price surge to $130, LTC is still well short of the $410 record high hit in 2021. Its price chart shows a constructive outlook (check out the Technical Analysis section below).\n\nIn other key developments, on-chain activity tracked by Glassnode shows a lower level of retail participation in BTC right than in November. That's encouraging for bulls looking for cues on whether the latest move above $100,000 is sustainable. Meanwhile, Lombard Finance is becoming more dominant in the bitcoin staking space, capturing a giant share of the total BTC staked this week.\n\nThe number of Ethereum's active addresses recently topped a March 2024 high, signaling a renewed uptick in the on-chain activity, according to IntoTheBlock data. Ether's price has crossed above $3,200 but is yet to clear the bearish trendline connecting the Dec. 16 and Jan. 6 highs.\n\nIn traditional markets, the yield on the benchmark U.S. 10-year Treasury note has dropped to 4.50%, revisiting Monday's low in a bullish move for risk assets. Those bullish on BTC may be hoping for U.S. core PCE inflation to come in softer-than-expected later today, driving the bond yield even lower.\n\nThat said, we will also get fourth-quarter GDP alongside the weekly jobless claims report. Meanwhile, European gas prices have surged to a 15-month high and could inject some volatility into risk assets. Stay alert!\n\nBy Shaurya Malwa\n\nETF Flows\n\nSpot BTC ETFs:\n\nSpot ETH ETFs\n\nSource: Farside Investors",
    "url": "https://www.coindesk.com/daybook-us/2025/01/30/crypto-daybook-americas-litecoin-leads-on-optimistic-etf-signal-as-market-rallies-after-powell-talks",
    "llm_analysis": {
        "entities": {
            "persons": [
                "Omkar Godbole",
                "Eric Balchunas",
                "Shaurya Malwa"
            ],
            "positions": [
                "Bloomberg Senior ETF analyst"
            ],
            "companies": [
                "Canary Capital",
                "Lombard Finance"
            ],
            "organizations": [
                "SEC",
                "Fed",
                "Glassnode",
                "IntoTheBlock",
                "Farside Investors"
            ]
        },
        "cryptocurrencies": [
            "LTC",
            "BTC",
            "ETH",
            "Bitcoin",
            "Ethereum",
            "Litecoin",
            "Tether"
        ],
        "impact_sentiment": "Bullish",
        "reasoning": "The news describes positive market performance with Litecoin leading gains, SEC acknowledgment of an ETF proposal, and overall optimistic factors including crypto-friendly policies and bullish technical indicators."
    }
}