{
    "title": "Hong Kong Joins Global Race With New Stablecoin Licensing Bill",
    "summary": "Hong Kong has been working on establishing a stablecoin regime since 2023.",
    "time": "2025-05-21T17:29:00",
    "author": "Camomile Shumba",
    "content": "Hong Kong passed a stablecoin bill that will enable the region to establish a licensing regime for fiat-backed stablecoin issuers.\n\n\"Hong Kongâ€™s stablecoins are backed by fiat currency as underlying assets, and we welcome global enterprises and institutions interested in issuing stablecoins to apply in Hong Kong,\" legislative council member Johnny Ng said on X on Wednesday.\n\nInstitutions are expected to be able to apply for a license from the Hong Kong Monetary Authority by the year-end.\n\nHong Kong has been working on establishing a stablecoin regime since 2023. The nation had published a consultation paper on stablecoin guidelines towards the end of 2023. It later introduced the Stablecoin Bill, which the Legislative Council of the Hong Kong Special Administrative Region passed in its third reading, Ng's post said.\n\nThe region has been looking to keep up with nations around the world that have been establishing their stablecoin regimes. The European Union started licensing stablecoin issuers last year after passing its wide-ranging bespoke crypto bill, called the Markets in Crypto Assets regulation (MiCa). Meanwhile, the U.S. has a stablecoin bill that is passing through Congress, and the U.K. has been gathering feedback on draft legislation that will also affect stablecoins.\n\nThe stablecoin sector has become the hottest trend in recent years, with both crypto and TradFi firms ramping up their exposure to the industry. Ben Reynolds, BitGo's managing director of stablecoins, said at Consensus 2025 that large banks are increasingly taking notice of the industry, largely out of fear that they will lose market share to the digital dollars.\n\nRead more: Banks Exploring Stablecoin Amid Fears of Losing Market Share, BitGo Executive Says",
    "url": "https://www.coindesk.com/policy/2025/05/21/hong-kong-joins-global-race-with-new-stablecoin-licensing-bill",
    "llm_analysis": {
        "entities": {
            "persons": [
                "Johnny Ng",
                "Ben Reynolds"
            ],
            "positions": [
                "legislative council member",
                "managing director of stablecoins"
            ],
            "companies": [
                "BitGo"
            ],
            "organizations": [
                "Hong Kong Monetary Authority",
                "Legislative Council of the Hong Kong Special Administrative Region",
                "European Union",
                "U.S. Congress",
                "Consensus 2025"
            ]
        },
        "cryptocurrencies": [],
        "impact_sentiment": "Bullish",
        "reasoning": "The news describes Hong Kong establishing a regulatory framework for stablecoins and welcoming global enterprises, which indicates positive regulatory developments that typically boost market confidence."
    }
}