{
    "title": "Crypto Daybook Americas: Bitcoin Buzzes With Anticipation Before Trump's Inauguration",
    "time": "2025-01-17T12:00:00",
    "author": "Omkar Godbole",
    "summary": "Your day-ahead look for Jan. 17, 2025",
    "content": "By Omkar Godbole (All times ET unless indicated otherwise)\n\nThe crypto world is buzzing as President-elect Donald Trump's inauguration nears. Bitcoin is holding above $100,000 and altcoins like SOL, ADA, LINK, XRP and LTC are shining as it's not just about a potential strategic bitcoin reserve anymore. Reports suggest Trump could announce crypto as a policy priority.\n\nThings are heating up for ether too. A blockchain address associated with Trump's World Liberty Finance (WLF) project snapped up nearly $10 million of ETH this week, according to Arkham Intelligence. And keep your eyes on layer-1 blockchain Near Protocol's NEAR. The token's supply dynamics look bullish, with the ratio of staked to unstaked NEAR rising, according to data source Flipside.\n\nOverall, the outlook for the crypto market is bullish, as Wednesday's U.S. CPI report has eased inflation concerns, allowing traders to focus on Trump's swearing-in. On-chain analysis from 21Shares shows there's still plenty of upside left for BTC.\n\nThat said, consider the possibility of a price drop if a major announcement doesn't materialize on Trump's first day.\n\n\"The macroeconomic backdrop remains supportive, with unemployment trending downward, inflation showing signs of easing, and the market riding a wave of enthusiasm tied to Trumpâ€™s inauguration,\" Valentin Fournier, an analyst at BRN, said. \"We maintain a bullish outlook for Q1, though a correction could happen this week if the new administration doesn't outline a solid action plan.\"\n\nNote that BTC is trading at a discount on Coinbase relative to Binance in a sign of weak demand from U.S. investors. Plus, Arkham Intelligence data shows a whale moved BTC worth over $1 billion to Coinbase on Thursday. Transfers to exchanges typically represent an investor intention to sell.\n\nAnd watch out for inflation worries creeping back. The U.S. PPI, which shows price pressures building up in the pipeline, rose above the CPI in December for the first time since 2022. Stay alert!\n\nBy Oliver Knight\n\nSpot BTC ETFs:\n\nSpot ETH ETFs\n\nSource: Farside Investors",
    "url": "https://www.coindesk.com/daybook-us/2025/01/17/crypto-daybook-americas-bitcoin-buzzes-with-anticipation-before-trumps-inauguration",
    "llm_analysis": {
        "entities": {
            "persons": [
                "Donald Trump",
                "Omkar Godbole",
                "Valentin Fournier",
                "Oliver Knight"
            ],
            "positions": [
                "President-elect",
                "analyst"
            ],
            "companies": [
                "Coinbase",
                "Binance",
                "World Liberty Finance",
                "21Shares",
                "BRN",
                "Arkham Intelligence",
                "Flipside",
                "Farside Investors"
            ],
            "organizations": []
        },
        "cryptocurrencies": [
            "Bitcoin",
            "BTC",
            "SOL",
            "ADA",
            "LINK",
            "XRP",
            "LTC",
            "ETH",
            "NEAR"
        ],
        "impact_sentiment": "Bullish",
        "reasoning": "The news describes a bullish outlook with Bitcoin holding above $100,000, positive policy expectations from Trump's inauguration, and analysts maintaining a bullish Q1 outlook despite potential short-term corrections."
    }
}