{
    "title": "Trump Family-Backed American Bitcoin to Go Public via Merger With Gryphon Digital",
    "time": "2025-05-12T12:27:00",
    "author": "James Van Straten",
    "summary": "Pre-market spikes follow news of strategic stock-for-stock transaction.",
    "content": "American Bitcoin, Hut 8’s majority-owned unit backed by the Trump family, will go public via a merger with Gryphon Digital Mining (GRYP).\n\nShares of Hut 8 Corp. (HUT) jumped 12% in pre-market trading, while Gryphon Digital Mining (GRYP) soared more than 200%, following the news.\n\nAmerican Data Center, which was owned by Eric Trump and Donald Trump Jr, merged their firm with American Bitcoin in March. The Trump brothers own 20% of American Bitcoin, while Hut 8 holds the remaining 80%.\n\nEric Trump is one of the headline speakers at Consensus 2025.\n\nThe stock-for-stock transaction will result in Gryphon acquiring American Bitcoin, with the combined company adopting the American Bitcoin name and trading on Nasdaq under the ticker “ABTC.”\n\nThe merger is expected to close as early as Q3 of 2025. American Bitcoin will retain its current leadership and board, including CEO Mike Ho, and remain focused on scaling low-cost bitcoin\nBTC\n$104,608.94\naccumulation.\n\n“This transaction marks the next step in scaling American Bitcoin as a purpose-built vehicle for low-cost Bitcoin accumulation at scale,” said Asher Genoot, CEO of Hut 8. “By taking American Bitcoin public, we expect to unlock direct access to dedicated growth capital independent of Hut 8’s balance sheet.”\n\nAfter the merger, existing shareholders of American Bitcoin are expected to own roughly 98% of the new company. Hut 8 will maintain majority ownership and serve as the exclusive infrastructure and operations partner.",
    "url": "https://www.coindesk.com/markets/2025/05/12/trump-family-backed-american-bitcoin-to-go-public-via-merger-with-gryphon-digital",
    "llm_analysis": {
        "entities": {
            "persons": [
                "Eric Trump",
                "Donald Trump Jr",
                "Mike Ho",
                "Asher Genoot"
            ],
            "positions": [
                "CEO",
                "headline speaker"
            ],
            "companies": [
                "American Bitcoin",
                "Gryphon Digital Mining",
                "Hut 8 Corp.",
                "American Data Center"
            ],
            "organizations": [
                "Nasdaq",
                "Consensus 2025"
            ]
        },
        "cryptocurrencies": [
            "Bitcoin",
            "BTC"
        ],
        "impact_sentiment": "Bullish",
        "reasoning": "The news reports significant stock price increases for both Hut 8 (12%) and Gryphon Digital Mining (200+%) following the merger announcement, indicating strong market confidence in the deal."
    }
}