{
    "title": "Crypto’s Market Penetration Tipping Point",
    "time": "2025-05-21T14:59:00",
    "author": "Alec Beckman",
    "summary": "Crypto is expected to cross the 10% threshold of adoption in 2025, marking the transition from niche to mainstream, says Psalion's Alec Beckman.",
    "content": "The digital assets market has transformed from a niche experiment into a global force reshaping finance, commerce, and technology. In May 2025, the global crypto market is valued at $3.05 trillion, growing at a pace on par with the internet boom in the 90s.\n\nHistorical adoption curves for technologies like the internet and smartphones demonstrate that 10% penetration often marks a tipping point, after which growth accelerates exponentially due to network effects and mainstream acceptance. Digital assets are now on this trajectory, driven by rising user adoption, institutional investment and innovative use cases. After years of public uncertainty, a pivotal milestone may be achieved this year: cryptocurrency user penetration can surpass the critical 10% threshold, estimated to reach 11.02% globally in 2025 by Statista, up from 7.41% in 2024.\n\nThe chart below compares the early user adoption curves of cryptocurrency and the internet. It highlights that crypto is growing at a significantly faster rate than the internet did in its early years.\n\nWith crypto expected to cross the 10% threshold of adoption in 2025, it is important to note that the 10% mark is not arbitrary —- it’s a well-documented tipping point in technology diffusion, rooted in Everett Rogers’ diffusion of innovations theory. This model shows that adoption shifts from early adopters (13.5%) to the early majority (34%) at around 10–15% penetration, marking the transition from niche to mainstream.\n\nCrossing 10% market penetration triggers rapid growth as infrastructure, accessibility and social acceptance align. Two very recent examples of this are the smartphone and the internet.\n\nFor cryptocurrencies, surpassing 10% penetration in 2025 would signal a similar inflection point, with network effects amplifying adoption — more users increase liquidity, merchant acceptance and developer activity, making crypto more practical for everyday transactions like payments and remittances.\n\nIn the U.S., 28% of adults (approximately 65 million people) own cryptocurrencies in 2025, nearly doubling from 15% in 2021. Additionally, 14% of non-owners plan to enter the market this year, and 66% of current owners intend to buy more, reflecting significant momentum. Globally, two out of three American adults are familiar with digital assets, signaling a sharp departure from its earlier speculative reputation. These figures underscore the growing mainstream acceptance of digital assets, aligning with the post-10% adoption surge observed in other transformative technologies.\n\nCrypto’s economic impact spans remittances, cross-border trade, and financial inclusion, particularly in Africa and Asia, where it empowers the unbanked.\n\nSeveral factors are propelling crypto past the 10% threshold:\n\nInstitutional and business involvement is accelerating digital assets’ mainstream integration. Major financial players like BlackRock and Fidelity are going all in on crypto services and have launched crypto exchange-traded funds (ETFs), with 72 ETFs awaiting SEC approval in 2025.\n\nBusinesses are adopting crypto payments to cut fees and reach global customers, particularly in retail and e-commerce. Examples include Burger King in Germany accepting bitcoin since 2019 and PayPal’s 2024 partnership with MoonPay for U.S. crypto purchases. Platforms like Coinbase Commerce and Triple-A, alongside partnerships like Ingenico and Crypto.com, enable merchants to accept crypto with local currency settlements, reducing volatility risks.\n\nDeFi activity has increased significantly in Sub-Saharan Africa, Latin America, and Eastern Europe. In Eastern Europe, DeFi accounted for over 33% of total crypto received, with the region placing third globally in year-over-year DeFi growth.\n\nDespite its momentum, digital assets face hurdles:\n\nStill, the trajectory is promising.\n\nBullish sentiment and crypto-friendly regulators, coupled with ETF momentum and payment integrations, underscore this trajectory. If innovation continues to balance out with trust, digital assets are likely to follow the internet and smartphone playbook — and grow even faster.",
    "url": "https://www.coindesk.com/coindesk-indices/2025/05/21/crypto-s-market-penetration-tipping-point",
    "llm_analysis": {
        "entities": {
            "persons": [
                "Alec Beckman",
                "Everett Rogers"
            ],
            "positions": [],
            "companies": [
                "Psalion",
                "BlackRock",
                "Fidelity",
                "Burger King",
                "PayPal",
                "MoonPay",
                "Coinbase Commerce",
                "Triple-A",
                "Ingenico",
                "Crypto.com"
            ],
            "organizations": [
                "Statista",
                "SEC"
            ]
        },
        "cryptocurrencies": [
            "bitcoin"
        ],
        "impact_sentiment": "Bullish",
        "reasoning": "The news describes cryptocurrency adoption crossing the critical 10% threshold, institutional investment accelerating, growing mainstream acceptance, and bullish sentiment with crypto-friendly regulators."
    }
}