{
    "title": "TON Jumps as Foundation Says VC Firms Invested $400M in the Token",
    "time": "2025-03-20T15:26:00",
    "author": "Krisztian Sandor",
    "summary": "Investors include Sequoia Capital, Ribbit, Benchmark, Kingsway, CoinFund, according to a press release.",
    "content": "Toncoin (TON), the native token of the Telegram-adjacent TON blockchain, spiked on Thursday as ecosystem organization The Open Network Foundation said several venture capital firms invested $400 million in the token.\n\nInvestors include Sequoia Capital, Ribbit, Benchmark and Kingsway, according to a press release shared with CoinDesk. Vy Capital, Draper Associates and Libertus Capital, CoinFund, Hypersphere, SkyBridge, and Karatage also participated in the round.\n\n\"These venture capital firms hold over $400 million worth of Toncoin, which is the native cryptocurrency of the TON Blockchain.Itâ€™s important to note that this is not a fundraising round. Instead, these VCs are placing their bets on the future success and utility of the TON Blockchain, its growing ecosystem, and its potential to provide real-world utility for crypto holdings, especially within Telegram,\" a Ton Foundation spokesperson told CoinDesk.\n\nTON's price jumped over 8% above $3.8 immediately following the announcement before paring some of the gains. The token's price was 2% up over the past 24 hours.\n\nThe TON network was originally developed by messaging app Telegram, but continued as an independent operation due to regulatory concerns after the company settled a lawsuit by the U.S. Securities and Exchange Commission (SEC) in 2020.\n\nTelegram CEO Pavel Durov was arrested in France in August as part of a complaint on Telegram's lack of moderation and cooperation with law enforcement. Durov regained access to his passport from authorities earlier this month. TON surged 20% on the news.\n\nDigital asset investment firm Pantera Capital said in May it made its \"largest investment ever\" in TON, without disclosing the value of the investment. The token's price is down 54% since its June peak above $8.",
    "url": "https://www.coindesk.com/markets/2025/03/20/ton-jumps-as-telegram-based-the-open-network-gets-usd400m-vc-investment",
    "llm_analysis": {
        "entities": {
            "persons": [
                "Pavel Durov"
            ],
            "positions": [
                "CEO"
            ],
            "companies": [
                "Sequoia Capital",
                "Ribbit",
                "Benchmark",
                "Kingsway",
                "CoinFund",
                "Vy Capital",
                "Draper Associates",
                "Libertus Capital",
                "Hypersphere",
                "SkyBridge",
                "Karatage",
                "Pantera Capital",
                "Telegram"
            ],
            "organizations": [
                "The Open Network Foundation",
                "U.S. Securities and Exchange Commission",
                "SEC",
                "Ton Foundation"
            ]
        },
        "cryptocurrencies": [
            "Toncoin",
            "TON"
        ],
        "impact_sentiment": "Bullish",
        "reasoning": "The news reports TON's price jumping over 8% immediately following the announcement of $400 million in venture capital investments and mentions previous 20% surges on positive news."
    }
}