{
    "title": "Over $5B Pouring into Bitcoin ETFs â€“ Thanks to Bold Directional Bets",
    "summary": "The 11 spot ETFs have attracted over $5.61 billion since early April, according to SoSoValue.",
    "time": "2025-05-17T14:18:00",
    "author": "Omkar Godbole",
    "content": "Billions of dollars have flowed into the U.S.-listed spot bitcoin\nBTC\n$101,819.00\nexchange-traded funds (ETFs) in recent weeks, as the cryptocurrency chalked out a sharp recovery rally from $75,000 to $100,000.\n\nMost of the investment is likely driven by bold, strategic bullish directional bets rather than market-neutral arbitrage plays, data analysis suggests.\n\nThe 11 spot ETFs drew in $2.97 billion in investor money in April, with an additional $2.64 billion flowing in so far this month, according to data source SoSoValue. That has boosted the net inflow since inception in January 2024 to over $41 billion.\n\nInstitutions have historically used these ETFs to set up non-directional arbitrage plays to profit from price discrepancies between futures and spot bitcoin markets. The so-called cash and carry arbitrage involves buying ETFs while simultaneously selling the CME futures to pocket the futures premium while bypassing price direction risks.\n\nBut inflows since early April seem driven by bullish directional bets, not arbitrage plays. That's reflected in the Commitment of Traders (COT) report published by the Commodities Futures Trading Commission (CFTC) every week.\n\nThe data shows leveraged funds, typically hedge funds and various types of money managers, including registered commodity trading advisors, have trimmed their net shorts to 14,139 contracts from 17,141 contracts in early April, according to data tracked by Tradingster.\n\nThe number of shorts would have risen if carry trades had primarily driven the net inflows.\n\n\"CFTC data shows leveraged funds didn't significantly increase short positions, indicating most flows were directional bets, not arbitrage,\" Imran Lakha, founder of Options Insight, in a blog post published on Deribit.\n\nThe shift in the nature of inflows in the ETFs suggests large players are increasingly using the ETFs to express a clear market outlook on bitcoin's future direction.\n\nBitcoin last changed hands at $102,700 at press time, according to CoinDesk data.",
    "url": "https://www.coindesk.com/markets/2025/05/17/over-usd5b-pouring-into-bitcoin-etfs-thanks-to-bold-directional-bets",
    "llm_analysis": {
        "entities": {
            "persons": [
                "Imran Lakha"
            ],
            "positions": [
                "founder"
            ],
            "companies": [
                "SoSoValue",
                "Deribit",
                "CoinDesk"
            ],
            "organizations": [
                "Commodities Futures Trading Commission",
                "CFTC",
                "Options Insight"
            ]
        },
        "cryptocurrencies": [
            "Bitcoin",
            "BTC"
        ],
        "impact_sentiment": "Bullish",
        "reasoning": "The news reports over $5.61 billion flowing into Bitcoin ETFs driven by bullish directional bets rather than arbitrage plays, indicating strong institutional confidence and market optimism."
    }
}