{
    "title": "SUI Surges on Trump-Affiliated World Liberty Financial Reserve Asset Deal",
    "time": "2025-03-06T14:49:00",
    "author": "Krisztian Sandor",
    "summary": "The DeFi protocol will add Sui assets to its token reserve and explore product development opportunities.",
    "content": "The native token of\nSUI\n$2.0579\nsurged on Thursday on news that Trump-affiliated decentralized finance protocol\nWLFI\n$0.1110\nstroke a \"strategic reserve deal\" with the layer-1 blockchain project.\n\nThe agreement includes WLFI adding Sui assets to its crypto holdings, the announcement said. The two projects will also explore \"product development opportunities.\"\n\nSUI jumped as much as 10% to near $3 before paring gains. Still it was up about 13% in the past 24 hours, being the best-performing asset in the broad-market CoinDesk 20 Index.\n\n\"We chose Sui for its American-born innovation combined with impressive scale and adoption,\" said Zak Folkman, co-founder of World Liberty Financial. â€œGiven our plans to support foundational DeFi assets in the coming months, collaborating with Sui was an obvious decision.\"\n\nWorld Liberty Financial has already accumulated various digital assets in its \"strategic token reserve,\" including wrapped bitcoin, ether\nETH\n$3,498.35\n, Tron's TRX, Chainlink's LINK as well as MOVE and ONDO tokens.",
    "url": "https://www.coindesk.com/markets/2025/03/06/sui-surges-on-trump-affiliated-world-liberty-financial-reserve-asset-deal",
    "llm_analysis": {
        "entities": {
            "persons": [
                "Zak Folkman"
            ],
            "positions": [
                "co-founder"
            ],
            "companies": [
                "World Liberty Financial"
            ],
            "organizations": [
                "CoinDesk 20 Index"
            ]
        },
        "cryptocurrencies": [
            "SUI",
            "WLFI",
            "Bitcoin",
            "ETH",
            "TRX",
            "LINK",
            "MOVE",
            "ONDO"
        ],
        "impact_sentiment": "Bullish",
        "reasoning": "The news explicitly states that SUI surged 10% and was up 13% in 24 hours following the strategic reserve deal announcement."
    }
}