{
    "title": "Trump-Linked Crypto Project Buys $775K Worth of SEI as Altcoin Accumulation Continues",
    "summary": "World Liberty Financial added SEI to its growing altcoin portfolio as it keeps accumulating and after it denied reports suggesting it sold ETH.",
    "time": "2025-04-13T17:57:00",
    "author": "Francisco Rodrigues",
    "content": "World Liberty Financial, the crypto venture backed by U.S. President Donald Trump’s family, purchased $775,000 worth of SEI tokens as its altcoin accumulation strategy keeps going.\n\nThe move was funded with USDC transferred from the project’s main wallet to a trading wallet that has been used in prior altcoin buys, according to fresh data from Arkham Intelligence.\n\nThe SEI purchase adds to a growing portfolio that includes not only the top two cryptocurrencies, bitcoin\nBTC\n$101,682.65\nand ether\nETH\n$3,320.11\n, but also TRX,\nMOVE\n$0.05388\n,\nONDO\n$0.6057\nand various other tokens.\n\nWorld Liberty Financial recently denied selling ether or any of its other positions after reports suggested a wallet belonging to the project sold around $8 million worth of the second-largest cryptocurrency.\n\nThe price of SEI jumped after the move was reported and is up more than 27% over the past week as a result to now trade at $0.178 per token.",
    "url": "https://www.coindesk.com/markets/2025/04/13/trump-linked-crypto-project-buys-usd775-000-worth-of-sei-as-altcoin-accumulation-continues",
    "llm_analysis": {
        "entities": {
            "persons": [
                "Donald Trump"
            ],
            "positions": [
                "U.S. President"
            ],
            "companies": [
                "World Liberty Financial"
            ],
            "organizations": [
                "Arkham Intelligence"
            ]
        },
        "cryptocurrencies": [
            "SEI",
            "BTC",
            "ETH",
            "TRX",
            "MOVE",
            "ONDO",
            "USDC"
        ],
        "impact_sentiment": "Bullish",
        "reasoning": "The news reports that SEI's price jumped more than 27% after the purchase and describes continued accumulation of altcoins, indicating positive market movement and confidence."
    }
}