{
    "title": "Metaplanet Plans a Further $21M Bond Sale to Buy More BTC",
    "time": "2025-05-09T08:40:00",
    "author": "Jamie Crawley",
    "summary": "Metaplanet has the largest BTC stash among publicly-traded companies outside North America",
    "content": "Japanese hotel firm Metaplanet (3350) said it plans to sell another $21.25 million worth of bonds to fund further bitcoin (BTC) purchases.\n\nThe Tokyo-based firm agreed to issue the debt to EVO FUND on May 9, making it the third such sale in the space of a week, following two issues of $25 million each.\n\nThe bonds will not bear any interest and have a redemption date of Nov. 9, Metaplanet announced in a post on X on Friday.\n\nThe firm's bitcoin stash currently sits at 5,555 BTC ($576 million), the 11th largest holding among publicly-traded companies and the largest of firms outside North America.\n\nMetaplanet shares closed 2.75% higher on Friday at 524 yen ($3.61), outperforming the Nikkei 225 which gained 1.56%.\n\nRead More: Strike CEO Mallers to Lead Bitcoin Investment Company Backed by Tether, Softbank, Brandon Lutnick",
    "url": "https://www.coindesk.com/markets/2025/05/09/metaplanet-plans-a-further-21m-bond-sale-to-buy-more-btc",
    "llm_analysis": {
        "entities": {
            "persons": [
                "Mallers",
                "Brandon Lutnick"
            ],
            "positions": [
                "CEO"
            ],
            "companies": [
                "Metaplanet",
                "EVO FUND",
                "Strike",
                "Tether",
                "Softbank"
            ],
            "organizations": [
                "Nikkei 225"
            ]
        },
        "cryptocurrencies": [
            "BTC",
            "Bitcoin"
        ],
        "impact_sentiment": "Bullish",
        "reasoning": "A publicly-traded company is raising additional funds specifically to purchase more bitcoin, indicating continued institutional buying confidence in the cryptocurrency."
    }
}