{
    "title": "Auradine Raises $153M Series C for Bitcoin Mining, AI Data Center Networking",
    "time": "2025-04-17T09:05:00",
    "author": "Jamie Crawley",
    "summary": "The funding round takes Auradine's total backing to $300 million.",
    "content": "Auradine, a maker of computing equipment for bitcoin\nBTC\n$106,892.83\nmining and AI applications, said it raised $153 million in a Series C funding round.\n\nThe Silicon Valley, California-based company also formed a new business group, AuraLinks AI, focused on open-standards to address cooling requirements of next-generation AI data centers.\n\nAI data centers and BTC mining share similarities in their operational requirements. Given the proliferation of AI in mainstream use in recent years, the subject of data centers is now commonplace in public discourse. This is significant for the cryptocurrency industry because most things that relate to AI data centers could also be applied to bitcoin mining.\n\n\"Our dual focus on Bitcoin and AI infrastructure places Auradine at the intersection of pivotal technologies that will reshape computing and energy utilization for decades to come,\" CEO Rajiv Khemani said in a statement.\n\nThe funding round, which took Auradine's total backing to $300 million, was led by StepStone Group and included another contribution from bitcoin miner MARA, as well as Maverick Silicon, Samsung Catalyst Fund and Qualcomm Ventures, among others.",
    "url": "https://www.coindesk.com/business/2025/04/17/auradine-raises-usd153m-series-c-for-bitcoin-mining-ai-data-center-networking",
    "llm_analysis": {
        "entities": {
            "persons": [
                "Rajiv Khemani"
            ],
            "positions": [
                "CEO"
            ],
            "companies": [
                "Auradine",
                "StepStone Group",
                "MARA",
                "Maverick Silicon",
                "Samsung Catalyst Fund",
                "Qualcomm Ventures"
            ],
            "organizations": [
                "AuraLinks AI"
            ]
        },
        "cryptocurrencies": [
            "Bitcoin",
            "BTC"
        ],
        "impact_sentiment": "Bullish",
        "reasoning": "The news reports a significant $153 million funding round for bitcoin mining infrastructure and highlights the company's dual focus on Bitcoin and AI, indicating strong market confidence and institutional backing."
    }
}