{
    "title": "U.S. Senate Banking Committee Sets Hearing on Crypto Legislation Next Week",
    "summary": "The congressional committee that was a roadblock in the previous session has scheduled a Feb. 26 hearing on \"bipartisan legislative frameworks\" for crypto.",
    "time": "2025-02-21T16:37:00",
    "author": "Jesse Hamilton",
    "content": "The U.S. Senate Banking Committee has scheduled a hearing to discuss bipartisan digital assets legislation next week, the panel announced.\n\nThis Senate committee was the one that became a bottleneck in the previous congressional session, but it's now run by Senator Tim Scott, a South Carolina Republican who supports crypto.\n\nThe hearing will feature testimony from witnesses including lawyers from Kraken and Lightspark.\n\nThe U.S. Senate Banking Committee has scheduled a hearing to discuss bipartisan digital assets legislation next week, the panel announced.\n\nThis Senate committee was the one that became a bottleneck in the previous congressional session, but it's now run by Senator Tim Scott, a South Carolina Republican who supports crypto.\n\nThe hearing will feature testimony from witnesses including lawyers from Kraken and Lightspark.\n\nMore For You\n\nInside Zcash: Encrypted Money at Planetary Scale\n\nA deep dive into Zcash's zero-knowledge architecture, shielded transaction growth, and its path to becoming encrypted Bitcoin at scale.\n\nWhat to know:\n\nIn 2025, Zcash evolved from niche privacy tech into a functioning encrypted-money network:\n\nIn 2025, Zcash evolved from niche privacy tech into a functioning encrypted-money network:\n\nAppeals Court Seems Unmoved by Sam Bankman-Friedâ€™s Claims of an Unfair Trial\n\nThe former FTX CEO, who is currently serving a 25-year sentence for fraud, has repeatedly claimed that the crypto exchange was solvent at the time of its bankruptcy.\n\nWhat to know:",
    "url": "https://www.coindesk.com/policy/2025/02/21/u-s-senate-banking-committee-sets-hearing-on-crypto-legislation-next-week",
    "llm_analysis": {
        "entities": {
            "persons": [
                "Tim Scott",
                "Sam Bankman-Fried"
            ],
            "positions": [
                "Senator",
                "CEO"
            ],
            "companies": [
                "Kraken",
                "Lightspark",
                "FTX"
            ],
            "organizations": [
                "U.S. Senate Banking Committee",
                "Appeals Court"
            ]
        },
        "cryptocurrencies": [
            "Zcash",
            "Bitcoin"
        ],
        "impact_sentiment": "Bullish",
        "reasoning": "The hearing on bipartisan crypto legislation with a supportive committee chair suggests positive regulatory developments for the cryptocurrency market."
    }
}