{
    "title": "BitGo Mulling IPO This Year: Bloomberg",
    "time": "2025-02-11T20:20:00",
    "author": "Stephen Alpher",
    "summary": "The crypto custody firm raised $100 million at a $1.75 billion valuation in 2023.",
    "content": "Alongside a number of other digital asset-related firms, institutional crypto custody company BitGo is considering an initial public offering as soon as this year, according to Bloomberg.\n\nAmong the backers of the Mike Belshe-led BitGo are Goldman Sachs, DRW Holdings, Redpoint Ventures and Valor Equity Partners. The company's most recent funding round in 2023 valued it at $1.75 billion.\n\nOther crypto firms mulling an IPO in the wake of bitcoin's move to $100,000 and a friendlier U.S. regulatory environment include exchanges Gemini, Kraken and Bullish (the parent of CoinDesk), and stablecoin issuer Circle.\n\nAlongside a number of other digital asset-related firms, institutional crypto custody company BitGo is considering an initial public offering as soon as this year, according to Bloomberg.\n\nAmong the backers of the Mike Belshe-led BitGo are Goldman Sachs, DRW Holdings, Redpoint Ventures and Valor Equity Partners. The company's most recent funding round in 2023 valued it at $1.75 billion.\n\nOther crypto firms mulling an IPO in the wake of bitcoin's move to $100,000 and a friendlier U.S. regulatory environment include exchanges Gemini, Kraken and Bullish (the parent of CoinDesk), and stablecoin issuer Circle.\n\nMore For You\n\nOwlTing: Stablecoin Infrastructure for the Future\n\nStablecoin payment volumes have grown to $19.4B year-to-date in 2025. OwlTing aims to capture this market by developing payment infrastructure that processes transactions in seconds for fractions of a cent.\n\nRipple Acquires Crypto Wallet Firm Palisade to Expand Institutional Payments Business\n\nWith the acquisition, Ripple aims to provide quickly-deployable wallets to boost fintech and corporate crypto payments, president Monica Long said in an interview.\n\nWhat to know:",
    "url": "https://www.coindesk.com/business/2025/02/11/bitgo-mulling-ipo-this-year-bloomberg",
    "llm_analysis": {
        "entities": {
            "persons": [
                "Mike Belshe",
                "Monica Long"
            ],
            "positions": [
                "president"
            ],
            "companies": [
                "BitGo",
                "Goldman Sachs",
                "DRW Holdings",
                "Redpoint Ventures",
                "Valor Equity Partners",
                "Gemini",
                "Kraken",
                "Bullish",
                "CoinDesk",
                "Circle",
                "OwlTing",
                "Ripple",
                "Palisade"
            ],
            "organizations": []
        },
        "cryptocurrencies": [
            "bitcoin"
        ],
        "impact_sentiment": "Bullish",
        "reasoning": "The news describes multiple crypto firms considering IPOs amid bitcoin's price surge to $100,000 and a friendlier regulatory environment, indicating growing institutional confidence and market expansion."
    }
}