{
    "title": "Solana ETF Applications Reach Next Stage in SEC Review",
    "time": "2025-02-11T19:35:00",
    "author": "Danny Nelson",
    "summary": "The regulator could reach a decision at the end of a 21 day comment period.",
    "content": "Another day, another once unthinkable crypto exchange traded fund filing. Several Solana ETF applications have become the latest such proposed investment vehicles to reach the starting gate.\n\nIn a regulatory filing Tuesday the Securities and Exchange Commission (SEC) opened up public comment on the \"Canary Solana Trust,\" a proposed ETF from Canary Capital that would bring SOL investing into mainstream finance. The SEC acknowledged similar filings from VanEck, 21Shares and Bitwise later in the day.\n\nThe filing amounts to a clock-setting for these companies' proposed investment vehicle. In 21 days the SEC will render a verdict (approval or denial) or, perhaps more likely, kick the decision can with deadline extensions.\n\nMarket observers are broadly bullish that SOL and other altcoins will win their own ETFs this year, but the exact timing and order is unclear. What's more seemingly apparent is the SEC's newfound willingness to look favorably upon the industry, and past the regulator's old misgivings under former Chair Gary Gensler.\n\nDonald Trump's return to the White House created an opening for Canary to act aggressively, CEO Steve McClurg previously told CoinDesk. The firm's looking to list altcoin ETFs for assets like Solana that would have been nonstarters under the old regime.\n\nGrayscale's prospective Solana ETF reached this starting gate last week, meaning its 21-day fate will come a few days before Canary's â€“ and likely be a \"canary in the coal mine\" for both.\n\n.\"While we can't predict the SEC's timeline or decision-making process, we suspect it will take some time to establish a comprehensive crypto regulatory framework. Once that framework is in place, we anticipate the SEC will begin making decisions on various tokens, including Solana,\" Canary's CEO Steve McClurg said.\n\nUPDATE (Feb. 11, 2025, 22:10 UTC): Adds additional application acknowledgements.",
    "url": "https://www.coindesk.com/business/2025/02/11/canary-s-solana-etf-reaches-next-stage-in-sec-review",
    "llm_analysis": {
        "entities": {
            "persons": [
                "Steve McClurg",
                "Gary Gensler",
                "Donald Trump"
            ],
            "positions": [
                "CEO",
                "former Chair"
            ],
            "companies": [
                "Canary Capital",
                "VanEck",
                "21Shares",
                "Bitwise",
                "Grayscale",
                "CoinDesk"
            ],
            "organizations": [
                "Securities and Exchange Commission",
                "SEC",
                "White House"
            ]
        },
        "cryptocurrencies": [
            "Solana",
            "SOL",
            "altcoins"
        ],
        "impact_sentiment": "Bullish",
        "reasoning": "The news describes market observers as 'broadly bullish' about SOL and altcoin ETFs, highlights the SEC's 'newfound willingness to look favorably upon the industry,' and notes aggressive action by firms under the new administration."
    }
}