{
    "title": "Bitcoin Jumps Above $91K After Trump's U.S. Crypto Reserve News Brings Bulls Back",
    "time": "2025-03-02T17:27:00",
    "author": "Aoyon Ashraf",
    "summary": "XRP, ETH, SOL and ADA price have also surged following Trump's announcement.",
    "content": "Bitcoin's\nBTC\n$103,891.83\nprice surged past $91,000 on Sunday after U.S. President Donald Trump announced a crypto strategic reserve for the world's biggest economy.\n\nIn his initial announcement, Trump announced XRP, Solana\nSOL\n$160.89\n, and\nADA\n$0.5407\nas cryptocurrencies to be included in the reserve and later said BTC and ether\nETH\n$3,489.96\nwould also be part of it.\n\nRead more: Donald Trump Names XRP, SOL, ADA, BTC and ETH as Part of U.S. Crypto Reserve\n\nXRP jumped 31% in the last 24 hours to trade around $2.80, while ADA price crossed above $1 and SOL above $160, both rising more than 20% on Sunday.\n\nMeanwhile, BTC was up 6% in the last 24 hours, finally trading above $91,000 after prices stuck near the 80,000 to the $84,000 range. ETH was above $2,400, rising nearly 10% in the same time period. The broader CoinDesk 20 Index (CD20) rose a whopping 17% in the last 24 hours.\n\nThe news would also help the prices of crypto-linked stocks such as Strategy (MSTR), Coinbase (COIN), Robinhood (HOOD), and bitcoin miners such as MARA Holdings (MARA), Riot Platforms (RIOT), and CleanSpark (CLSK).\n\nTrump's move will likely bring bullish sentiment back into the digital assets space, which had been languishing for a week.\n\nThe crypto prices started to show signs of life on Friday when the white house said Trump would host a crypto summit on March 7. Summit attendees are set to include â€œprominent founders, CEOs, and investors from the crypto industry.\n\nRead more: Crypto Prices Show Signs of Recovery With Bitcoin Above $84k Amid Trump's Summit Plans",
    "url": "https://www.coindesk.com/markets/2025/03/02/bitcoin-jumps-above-usd91k-after-trump-establishes-u-s-crypto-reserves",
    "llm_analysis": {
        "entities": {
            "persons": [
                "Donald Trump"
            ],
            "positions": [
                "U.S. President"
            ],
            "companies": [
                "Strategy (MSTR)",
                "Coinbase (COIN)",
                "Robinhood (HOOD)",
                "MARA Holdings (MARA)",
                "Riot Platforms (RIOT)",
                "CleanSpark (CLSK)"
            ],
            "organizations": [
                "white house"
            ]
        },
        "cryptocurrencies": [
            "Bitcoin",
            "BTC",
            "XRP",
            "Solana",
            "SOL",
            "ADA",
            "ether",
            "ETH"
        ],
        "impact_sentiment": "Bullish",
        "reasoning": "The news describes significant price surges across multiple cryptocurrencies following Trump's announcement of a U.S. crypto reserve and states the move will likely bring bullish sentiment back into the digital assets space."
    }
}