{
    "title": "Crypto Daybook Americas: Can Bitcoin's Regulatory Worry be Bullish for DeFi Tokens?",
    "time": "2025-05-06T11:15:00",
    "author": "Omkar Godbole",
    "summary": "Your day-ahead look for May 6, 2025",
    "content": "By Omkar Godbole (All times ET unless indicated otherwise)\n\nAs bitcoin (BTC) and the wider crypto market await the Fed's rate decision on Wednesday, an anomaly has emerged that could weigh heavily on market mood: renewed doubt over the passing of U.S. crypto regulation.\n\nEarly Tuesday, CoinDesk reported that Senate Democrats are hesitant to push forward landmark stablecoin legislation, citing concerns over President Donald Trump's growing personal gains from his crypto ventures.\n\nWhen Trump took office, many observers felt crypto regulation would proceed smoothly. Looking back, that optimism was probably misplaced. With the president actively involved in digital assets through family-linked projects like WLFI and memecoins, opposition has mounted, potentially slowing the regulatory progress.\n\nThat might lead investors to reprice regulatory uncertainty just as charts for BTC and XRP are signaling pullback risks. Additionally, according to CryptoQuant, there are signs of renewed weakness in bitcoin demand from U.S.-based investors.\n\n\"Over the past month, the premium recovered significantly but is now dropping again â€” aligning with the recent BTC price correction,\" CryptoQuant contributor AbramChart said.\n\nOn the positive side, U.S.-listed spot bitcoin exchange-traded funds (ETFs) marked three straight days of net inflows.\n\nActing CFTC Chairman Caroline Pham told crypto journalist Eleanor Terret that the derivatives market regulator plans to observe a handful of tokenization pilot programs to evaluate the technology and see how well tokenized assets function in the real world.\n\nSpeaking of traditional markets and macro, Taiwan dollar forward contracts signal extreme pressure on the U.S. dollar, meaning the greenback could continue to weaken against the Asian currency and probably major currencies like the euro. The broad-based USD weakness may act as a tailwind for crypto. FX market volatility could drive investors to gold and perhaps bitcoin, too, unless it leads to a broad-based risk-off, in which case BTC may feel the heat.\n\nThe other bullish development is the U.S. Treasury Secretary Scott Bessent's comments that U.S. rates now carry sovereign credit risk and not just long-term growth and inflation expectations. In other words, rates are artificially high because the U.S. government itself is now the risk premium, as pseudonymous observer EndGame Macro said. So, a shift away from U.S. assets and into alternative investments could continue. Stay alert!\n\nCoinDesk's Consensus is taking place in Toronto on May 14-16. Use code DAYBOOK and save 15% on passes.\n\nBy Shaurya Malwa\n\nSpot BTC ETFs:\n\nSpot ETH ETFs\n\nSource: Farside Investors",
    "url": "https://www.coindesk.com/daybook-us/2025/05/06/crypto-daybook-americas-bitcoin-threatened-by-regulation-hiccup-weakening-demand",
    "llm_analysis": {
        "entities": {
            "persons": [
                "Omkar Godbole",
                "Donald Trump",
                "AbramChart",
                "Caroline Pham",
                "Eleanor Terret",
                "Scott Bessent",
                "EndGame Macro",
                "Shaurya Malwa"
            ],
            "positions": [
                "Acting CFTC Chairman",
                "U.S. Treasury Secretary",
                "crypto journalist",
                "CryptoQuant contributor",
                "pseudonymous observer"
            ],
            "companies": [
                "CoinDesk",
                "Farside Investors"
            ],
            "organizations": [
                "Senate Democrats",
                "Fed",
                "CFTC",
                "U.S. Treasury",
                "U.S. government",
                "Consensus"
            ]
        },
        "cryptocurrencies": [
            "Bitcoin",
            "BTC",
            "XRP",
            "ETH"
        ],
        "impact_sentiment": "Consolidation",
        "reasoning": "The news presents mixed signals with regulatory uncertainty and weakening BTC demand weighing on markets, while USD weakness and potential capital rotation into alternatives provide bullish counterpoints."
    }
}