{
    "title": "Crypto Exchange Gemini Hires Brad Vopni to Lead Institutional Push",
    "time": "2025-05-07T13:00:00",
    "author": "Will Canny",
    "summary": "Vopni will be responsible for overseeing and executing the firm's institutional strategy.",
    "content": "Crypto exchange Gemini has hired Brad Vopni as head of institutional, the company told CoinDesk in an exclusive interview.\n\nVopni will be responsible for overseeing and executing the firm's institutional strategy.\n\nGemini is already working with exchange-traded fund (ETF) providers such as VanEck, Purpose, Evolve, 7RCC, and Monochrome, the company said.\n\n\"With a crypto-native platform offering a diverse set of products founded with safety, security and compliance in mind, Gemini is well positioned to serve the growing institutional community wherever they are along their crypto journey, with a focus on delivering an exemplary client experience,\" Vopni said in emailed comments.\n\nPrior to joining Gemini, Vopni spent 6 years as head of digital assets at Hudson River Trading, one of the largest global electronic trading firms, where he led the firm’s expansion into the crypto space.\n\nHe joined Hudson River after leading capital markets at NextShares LLC, where he played a key role in the development and launch of the industry’s first actively-managed, portfolio-protected exchange-traded product.\n\nGemini hired Dan Chen as its new chief financial officer in March.\n\nRead more: Gemini Hires New CFO as It Prepares for Potential IPO\n\nDisclaimer: Parts of this article were generated with the assistance from AI tools and reviewed by our editorial team to ensure accuracy and adherence to our standards. For more information, see CoinDesk’s full AI Policy.",
    "url": "https://www.coindesk.com/business/2025/05/07/crypto-exchange-gemini-hires-brad-vopni-to-lead-institutional-push",
    "llm_analysis": {
        "entities": {
            "persons": [
                "Brad Vopni",
                "Dan Chen"
            ],
            "positions": [
                "head of institutional",
                "head of digital assets",
                "chief financial officer"
            ],
            "companies": [
                "Gemini",
                "Hudson River Trading",
                "NextShares LLC",
                "VanEck",
                "Purpose",
                "Evolve",
                "7RCC",
                "Monochrome"
            ],
            "organizations": [
                "CoinDesk"
            ]
        },
        "cryptocurrencies": [],
        "impact_sentiment": "Bullish",
        "reasoning": "The hiring of an experienced institutional leader and existing partnerships with major ETF providers signals growing institutional adoption and confidence in the crypto market."
    }
}