{
    "title": "Sell in May? Bitcoin Tops $107K, Could Hit Record Highs This Summer Say Analysts",
    "summary": "Regulatory tailwinds, persistent ETF and corporate buying, Fed rate decisions and Trump's looming tariff deadline are setting the crypto market up for an eventful next few months.",
    "time": "2025-05-20T20:43:00",
    "author": "Krisztian Sandor",
    "content": "\"Sell in May and go away,\" goes the Wall Street adage for equity markets every summer. For bitcoin\nBTC\n$101,731.44\n, though, some analysts say this season could mark a break from tradition.\n\n\"As we get into the European summer months, the sense is it's more likely a case of 'buy in May and go away' than any significant headwinds or selling pressure,\" said Paul Howard, director at crypto trading firm Wincent in a market note.\n\nA confluence of positive regulatory developments around digital assets in the U.S. and increasing institutional buying both via exchange-traded funds and spot allocation is poised to push BTC higher in the next months, Howard said.\n\nU.S.-traded spot bitcoin ETFs, for example, pulled in $667 million in net inflows on Monday with BTC pausing just below its January record, underscoring persistent demand, he noted. The vehicles attracted $3.3 billion in May, per SoSoValue. On top of that, there's been a flurry of companies joining Michael Saylor's Strategy (MSTR) adding bitcoin to their treasury, financed by debt and stock issuances.\n\n\"As we edge closer to a $4 trillion market cap for digital assets, we will see BTC cross all-time-highs in the coming weeks,\" Howard said. The total crypto market cap currently stands at around $3.3 trillion, per TradingView data.\n\nHistorically, summer months have been slow for crypto assets, but macro and political forces are also converging in ways that could disrupt the typical seasonal lull, analysts at crypto analytics firm Kaiko pointed out.\n\nThe Federal Reserveâ€™s next interest rate decision in June will precede Donald Trump's July 9 tariff deadline for trade partners, both of which could trigger market-wide volatility, the report said.\n\nBitcoin options markets are already flashing signs of investor anticipation, Kaiko analysts said. Strike prices at $110,000 and $120,000 for the June 27 expiry have drawn heavy volume, suggesting bets on BTC making a record-breaking move, the report noted.\n\nBitcoin briefly topped $107,000 during the Tuesday session, gaining 1.2% over the past 24 hours and trading just 2% below its January record high.",
    "url": "https://www.coindesk.com/markets/2025/05/20/sell-in-may-bitcoin-tops-107k-could-hit-record-highs-this-summer-say-analysts",
    "llm_analysis": {
        "entities": {
            "persons": [
                "Paul Howard",
                "Michael Saylor"
            ],
            "positions": [
                "director"
            ],
            "companies": [
                "Wincent",
                "Strategy (MSTR)"
            ],
            "organizations": [
                "Federal Reserve",
                "Kaiko",
                "SoSoValue",
                "TradingView"
            ]
        },
        "cryptocurrencies": [
            "Bitcoin",
            "BTC"
        ],
        "impact_sentiment": "Bullish",
        "reasoning": "The news describes positive regulatory developments, institutional buying via ETFs, corporate treasury allocations, and analyst predictions of Bitcoin reaching all-time highs in the coming weeks."
    }
}