{
    "title": "Crypto Daybook Americas: The 2 Factors That Suggest a Quarter-End BTC Price Rally",
    "time": "2025-03-13T11:15:00",
    "author": "Omkar Godbole",
    "summary": "Your day-ahead look for March 13, 2025",
    "content": "By Omkar Godbole (All times ET unless indicated otherwise)\n\nThe crypto market has steadied over the past two days, with bitcoin briefly topping the 200-day simply moving average at $84,000 early today. Wednesday's softer-than-expected U.S. CPI release aided the sentiment by validating traders' pricing of four interest-rate cuts by the Federal Reserve this year.\n\nThe past 24 hours' recovery was led by the memecoin sector, followed by tokens of layer-1 and layer-2 blockchains as well as AI tokens, according to data source Velo.\n\nStill, issues such as President Trump's tariffs, U.S. recession concerns and the bond-market volatility that recently rocked risk assets, including BTC, remain to cast doubt on the sustainability of the market recovery. That said, at least two factors suggest otherwise.\n\nThe first is the quarter-end rebalancing. The Nasdaq and S&P 500 are down 6% and 4.8%, respectively, this quarter, while the 10-year Treasury note is up 5%. That means funds mandated to maintain a specific asset allocation mix are now overweight bonds and will probably rebalance by buying equities and selling bonds as the quarter end nears.\n\nThose actions will push bond yields and stock prices higher and could bode well for bitcoin and the broader crypto market, given the strong correlation between BTC and the technology stocks.\n\nThe other factor is the yen, which has come under pressure since CoinDesk noted the potential for renewed crypto market stability on the back of overstretched bullish positioning in the Japanese currency. The yen, seen as a haven investment, may remain under pressure as the potential quarter-end rebalancing lifts U.S. bond yields. In other words, risk-off stemming from the JPY strength and the resulting unwinding of the yen carry trades may be over for now.\n\nPositive net global liquidity could also grease risk-taking.\n\n\"Net global liquidity, largely due to China and the U.S., is increasing,\" Two Prime, an SEC-registered investment adviser, said in a Telegram chat. \"This may counteract some of the effects of the yen tradeâ€™s unwind. In addition, as the U.S. gets its own rates and inflation under better control, which has already started to incrementally trend down over the past few months, it will reduce pressure on other central bank bonds and slow rate growth on yen borrow.\"\n\nStill, traders need to be vigilant for volatility, as Deribit's BTC-listed options market tracked by Amberdata shows significant negative dealer gamma between $81,000 and $87,000. Dealers are likely to trade in the direction of the market to maintain their overall exposure neutral, adding to price swings.\n\nThe U.S. is set to publish the February producer price index (PPI) report and the weekly jobless claims later today. A hotter-than-expected PPI, representing pipeline inflation, may inject downside volatility into risk assets. Stay alert!\n\nBy Shaurya Malwa\n\nSpot BTC ETFs:\n\nSpot ETH ETFs\n\nSource: Farside Investors",
    "url": "https://www.coindesk.com/daybook-us/2025/03/13/crypto-daybook-americas-the-2-factors-that-suggest-a-quarter-end-btc-price-rally",
    "llm_analysis": {
        "entities": {
            "persons": [
                "Omkar Godbole",
                "Shaurya Malwa"
            ],
            "positions": [
                "President"
            ],
            "companies": [
                "CoinDesk",
                "Two Prime",
                "Deribit",
                "Amberdata",
                "Farside Investors"
            ],
            "organizations": [
                "Federal Reserve",
                "SEC"
            ]
        },
        "cryptocurrencies": [
            "bitcoin",
            "BTC"
        ],
        "impact_sentiment": "Bullish",
        "reasoning": "The article highlights multiple factors suggesting a potential quarter-end BTC price rally including quarter-end rebalancing favoring equities, yen weakness supporting risk assets, and positive net global liquidity."
    }
}