{
    "title": "CME Group to Launch Solana Futures as Demand for Crypto Derivatives Grows",
    "time": "2025-02-28T14:28:00",
    "author": "Helene Braun",
    "summary": "CME Group expands its crypto offerings with Solana futures, set to debut in March.",
    "content": "CME Group, the world's largest derivatives marketplace, plans to introduce Solana\nSOL\n$161.46\nfutures on March 17, expanding its suite of cryptocurrency derivatives, it said in a press release on Friday. The new contracts, pending regulatory review, will allow traders to manage SOL price risk with two contract sizes: 25 SOL and 500 SOL.\n\n“With the launch of our new SOL futures contracts, we are responding to increasing client demand for a broader set of regulated products,” said Giovanni Vicioso, CME Group’s Global Head of Cryptocurrency Products.\n\nThe contracts will be cash-settled, using the CME CF Solana-Dollar Reference Rate, which tracks SOL’s price daily at 4:00 p.m. London time. CME already offers bitcoin and ether futures, which have seen significant growth in trading activity. The firm reported an average daily volume of 202,000 contracts this year, up 73% from 2024.\n\nIndustry leaders view the move as a step toward greater institutional adoption of crypto. Teddy Fusaro, president of Bitwise Asset Management, noted that CME’s crypto derivatives have helped pave the way for regulated financial products, including ETFs. Kyle Samani of Multicoin Capital added that such products give sophisticated investors more tools to manage risk and exposure.\n\nWith Solana gaining traction among developers and investors, the addition of SOL futures highlights the increasing demand for regulated crypto trading products. It could also pave the way for SOL exchange-traded funds (ETFs) to be approved by the Securities and Exchange Commission (SEC).\n\n\"CME’s decision to list SOL contracts today significantly increases the possibility that corresponding spot ETF applications could be approved in the foreseeable future,\" said Sui Chung, CEO of CF Benchmarks.\n\n\"While an exact timeline for approval is hard to discern, it’s probable the SEC will want to see several months’ worth of trading on the CME and be satisfied that the futures correlate with the spot market before it looks to approve ETF applications for SOL.\"\n\nDisclaimer: Parts of this article were generated with the assistance from AI tools and reviewed by our editorial team to ensure accuracy and adherence to our standards. For more information, see CoinDesk’s full AI Policy.",
    "url": "https://www.coindesk.com/markets/2025/02/28/cme-group-to-launch-solana-futures-as-demand-for-crypto-derivatives-grows",
    "llm_analysis": {
        "entities": {
            "persons": [
                "Giovanni Vicioso",
                "Teddy Fusaro",
                "Kyle Samani",
                "Sui Chung"
            ],
            "positions": [
                "Global Head of Cryptocurrency Products",
                "president",
                "CEO"
            ],
            "companies": [
                "CME Group",
                "Bitwise Asset Management",
                "Multicoin Capital",
                "CF Benchmarks"
            ],
            "organizations": [
                "Securities and Exchange Commission",
                "SEC"
            ]
        },
        "cryptocurrencies": [
            "Solana",
            "SOL",
            "bitcoin",
            "ether"
        ],
        "impact_sentiment": "Bullish",
        "reasoning": "The launch of regulated Solana futures by CME Group is described as responding to increasing client demand and paving the way for greater institutional adoption and potential ETF approvals."
    }
}