{
    "title": "Crypto Daybook Americas: Bitcoin's Bullish Seasonality Nears as $31.8B Dry Powder Awaits",
    "time": "2025-03-26T11:15:00",
    "author": "Omkar Godbole",
    "summary": "Your day-ahead look for March 26, 2025",
    "content": "By Omkar Godbole (All times ET unless indicated otherwise)\n\nThe sun shone on crypto markets early Wednesday, with bitcoin having another go at $88,000 amid growing chatter about bullish seasonality factors as March draws to a close and the second quarter looms.\n\nThe last 10 years of price data tracked by analyst Miles Deutscher show April as the turning point for the market, with a 75% chance of upside between now and year-end. The pattern was noted by QCP Capital as well, which pointed to the second quarter, and April in particular, as bullish for crypto.\n\n\"The S&P 500 has delivered an average annualized return of 19.6% in Q2, while Bitcoin has also recorded its second-best median performance during this stretch - again, trailing only Q4,\" the Singapore-based firm said on Telegram.\n\nSeasonality factors are not as reliable as standalone indicators, but when coupled with other signs, such as the recent halt in selling by long-term holders, they appear credible.\n\nThe so-called 1Y+HODL wave indicator, which tracks the proportion of Bitcoin addresses (or wallets) that have kept their BTC for at least one year, has turned upward, signaling a shift into a holding strategy, according to data source Bitbo Charts. See Chart of the Day, below, too.\n\nReports that the Federal Deposit Insurance Corporation (FDIC) is drafting rules to remove reputational risk from its bank supervision were labeled â€œa big win for crypto\" by White House crypto czar David Sacks. \"In practice, this vague and subjective criteria was used to justify the debanking of lawful crypto businesses through Operation Chokepoint 2.0,\" Sacks said on X.\n\nSpeaking of the wider market, social media talk about stablecoins has picked up, with observers pointing to $31.8 billion in stablecoins sitting on the sidelines on Binance as potential dry powder waiting for a catalyst. BlackRock's decision to debut a physical bitcoin exchange-traded product in Europe with a reduced total expense ratio of 15 bps is seen as highly positive as well, considering fees are generally higher there than in the U.S., capping widespread adoption.\n\nStill, macroeconomic uncertainty has the potential to play spoilsport and keep animal spirits at bay. While recent media reports suggest President Donald Trump's expected reciprocal tariffs on April 2 may be softer than expected, there is still considerable confusion concerning the legality of the tariffs and the countries and sectors that will be targeted.\n\nThe deeper slide in U.S. consumer confidence in March and the death cross in the USD/JPY pair, indicating a strengthening of the yen, a haven currency, ahead, don't help matters either. So stay alert!\n\nBy Shaurya Malwa\n\nSpot BTC ETFs:\n\nSpot ETH ETFs\n\nSource: Farside Investors",
    "url": "https://www.coindesk.com/daybook-us/2025/03/26/crypto-daybook-americas-bitcoin-owners-hodl-as-sunny-second-quarter-nears",
    "llm_analysis": {
        "entities": {
            "persons": [
                "Omkar Godbole",
                "Miles Deutscher",
                "David Sacks",
                "Donald Trump",
                "Shaurya Malwa"
            ],
            "positions": [
                "White House crypto czar"
            ],
            "companies": [
                "QCP Capital",
                "Binance",
                "BlackRock",
                "Federal Deposit Insurance Corporation"
            ],
            "organizations": [
                "S&P 500",
                "Farside Investors"
            ]
        },
        "cryptocurrencies": [
            "Bitcoin",
            "BTC"
        ],
        "impact_sentiment": "Bullish",
        "reasoning": "The news highlights multiple positive factors including bullish seasonality patterns, reduced regulatory risk, institutional adoption, and significant stablecoin liquidity waiting to enter the market."
    }
}