{
    "title": "Ether Has Underperformed, but Total Value Locked on Ethereum Is Rising: Citi",
    "time": "2025-02-11T08:36:00",
    "author": "Will Canny",
    "summary": "Ether has dropped over 20% this year, but fundamentals are improving, the report said.",
    "content": "ghuihzjinhzEther\nETH\n$3,494.92\nhas underperformed year-to-date, declining over 20%, but fundamentals are improving and total value locked (TVL) on the Ethereum blockchain has risen dramatically, Wall Street bank Citi (C) said in a research report Monday.\n\n\"While user activity has been volatile in recent weeks, the fundamental backdrop is not all that murky,\" analysts led by Alex Saunders wrote.\n\nCiti noted that TVL on the Ethereum network has risen sharply, while ether exchange-traded funds (ETFs) are still seeing inflows, and search interest is rising.\n\nFollowing the U.S. election in November, ether ETF flows turned positive, the report noted, with total inflows of $3.2 billion since their July launch.\n\nStronger user growth on layer-2s and rival blockchain's such as Solana has raised questions about Ethereum's competitive advantage, the report said.\n\nPresident Trump's World Liberty Financial holds more than $200 million of ether, and this could be viewed as \"additional motivation for ensuring the U.S. strengthens its support for the crypto industry,\" the bank said.\n\n\"Relative ETH and altcoin performance may serve as a gauge for how optimistic the industry is regarding follow-through on regulatory clarity in the U.S.,\" the report added.\n\nCiti noted that weakness in ether has coincided with an increase in bitcoin\nBTC\n$103,962.30\ndominance, which is now at multi-year highs above 60%.\n\nRead more: Ethereum Faces 'Intense' Competition From Other Networks: JPMorgan",
    "url": "https://www.coindesk.com/markets/2025/02/11/ether-has-underperformed-but-total-value-locked-on-ethereum-is-rising-citi",
    "llm_analysis": {
        "entities": {
            "persons": [
                "Alex Saunders",
                "Trump"
            ],
            "positions": [
                "President",
                "analysts"
            ],
            "companies": [
                "Citi",
                "World Liberty Financial",
                "JPMorgan"
            ],
            "organizations": [
                "Wall Street bank"
            ]
        },
        "cryptocurrencies": [
            "Ether",
            "ETH",
            "Ethereum",
            "Solana",
            "bitcoin",
            "BTC",
            "altcoin"
        ],
        "impact_sentiment": "Bullish",
        "reasoning": "The report highlights improving fundamentals including rising total value locked, positive ETF inflows of $3.2 billion, and potential regulatory support despite short-term price weakness."
    }
}