{
    "title": "Metaplanet Issues $13M Zero-Coupon Bond to Buy More Bitcoin",
    "time": "2025-03-31T13:52:00",
    "author": "James Van Straten",
    "summary": "The Japanese hotel firm secures 15.5% weighting in crypto-focused exchange-traded fund.",
    "content": "Japanese hotel firm Metaplanet (3350) has issued a 2 billion yen ($13.3 million) zero-coupon ordinary bond, with proceeds earmarked for additional bitcoin\nBTC\n$103,929.21\npurchases. The bond is scheduled to redeem on Sept. 30.\n\nIn addition, Metaplanet has been added to the BetaShares Crypto Innovators ETF (CRYP), a fund with over $50 billion in assets under management, according to CEO Simon Gerovich.\n\nMetaplanet holds the largest weighting in the ETF at 15.5%, surpassing notable industry names such as Strategy (MSTR) and Coinbase (COIN), which take the second and third spots, respectively.\n\nThe ETF is traded on the Australian Securities Exchange (ASX) and offers investors exposure to companies operating at the forefront of the crypto and blockchain sectors. While, the CRYP ETF is down 23% year-to-date.\n\nMetaplanet is currently ranked as the tenth-largest publicly listed holder of bitcoin, with a treasury of 3,200 BTC.\n\nDisclaimer: Parts of this article were generated with the assistance from AI tools and reviewed by our editorial team to ensure accuracy and adherence to our standards. For more information, see CoinDeskâ€™s full AI Policy.",
    "url": "https://www.coindesk.com/markets/2025/03/31/metaplanet-issues-usd13m-zero-coupon-bond-to-buy-more-bitcoin",
    "llm_analysis": {
        "entities": {
            "persons": [
                "Simon Gerovich"
            ],
            "positions": [
                "CEO"
            ],
            "companies": [
                "Metaplanet",
                "Strategy",
                "Coinbase"
            ],
            "organizations": [
                "BetaShares Crypto Innovators ETF",
                "Australian Securities Exchange"
            ]
        },
        "cryptocurrencies": [
            "Bitcoin",
            "BTC"
        ],
        "impact_sentiment": "Bullish",
        "reasoning": "The news describes a company issuing bonds specifically to purchase more Bitcoin and achieving the largest weighting in a crypto-focused ETF, indicating institutional confidence and capital inflow into the cryptocurrency market."
    }
}