{
    "title": "Strive Closes $750M Investment Deal to Power 'Alpha-Generating' Bitcoin Strategy",
    "summary": "Investment sets stage for $1.5 billion total proceeds and strategic bitcoin accumulation with alpha-generating focus",
    "time": "2025-05-27T13:00:00",
    "author": "James Van Straten",
    "content": "Strive closed a $750 million private investment in public equity (PIPE) round, with an option to increase the financing by another $750 million if the warrants are exercised.\n\nThis capital will fund Strive’s initial wave of bitcoin\nBTC\n$101,860.90\nbuys as the firm builds its bitcoin treasury. The Vivek Ramaswamy-founded firm will deploy alpha-generating strategies aimed at outperforming bitcoin.\n\nCEO Matt Cole emphasized that Strive’s approach demands a new valuation framework. This strategy is driven by acquisitions of undervalued biotech firms, distressed bitcoin claims—including Mt. Gox claims via a partnership with 117 Partners LLC—and discounted tranches of structured bitcoin credit.\n\nLast week, the firm said it is eyeing $7.9 billion worth of Mt. Gox bitcoin claims as it looks to build its bitcoin treasury and go public via a merger with Asset Entities (ASST).\n\nRead more: Strive Eyes $7.9B Distressed Mt. Gox Bitcoin Claims to Accumulate Discounted BTC\n\nThe PIPE was priced at $1.35 per share, a 121% premium over ASST’s pre-announcement closing price, and carries no debt financing to preserve future leverage capacity.\n\nCole is set to present these strategies at the bitcoin for Corporations Symposium in Las Vegas.\n\nCantor Fitzgerald & Co. served as exclusive financial advisor and placement agent, with legal counsel provided by Davis Polk, DLA Piper, and Bevilacqua PLLC.\n\nRead more: Strive Asset Management to Go Public, Launch Bitcoin Treasury Strategy With Merger",
    "url": "https://www.coindesk.com/markets/2025/05/27/strive-closes-usd750m-investment-deal-to-power-alpha-driven-bitcoin-strategy",
    "llm_analysis": {
        "entities": {
            "persons": [
                "Vivek Ramaswamy",
                "Matt Cole"
            ],
            "positions": [
                "CEO"
            ],
            "companies": [
                "Strive",
                "Asset Entities",
                "Cantor Fitzgerald & Co.",
                "Davis Polk",
                "DLA Piper",
                "Bevilacqua PLLC",
                "117 Partners LLC"
            ],
            "organizations": [
                "Mt. Gox",
                "bitcoin for Corporations Symposium"
            ]
        },
        "cryptocurrencies": [
            "Bitcoin",
            "BTC"
        ],
        "impact_sentiment": "Bullish",
        "reasoning": "The news describes a $750 million investment specifically for bitcoin accumulation and alpha-generating strategies, indicating institutional buying and market confidence in bitcoin."
    }
}