{
    "title": "Crypto Consortium T3 FCU Helps Spanish Authorities Freeze $26.4M Linked to Crime Syndicate",
    "summary": "Authorities in Spain say they've arrested 23 people and seized $26.4 million thanks to assistance from T3.",
    "time": "2025-01-30T06:18:00",
    "author": "Sam Reynolds",
    "content": "Spanish authorities are crediting the T3 Financial Crime Unit, a consortium made up of Tron, Tether, and TRM Labs, for helping take down a multinational European financial crime syndicate.\n\nAccording to Spain's Guardia Civil, the crime syndicate operated across multiple European jurisdictions, providing cash-to-crypto laundering services for criminal enterprises.\n\nT3 said it seized $26.4 million, calling it the most significant coordinated freeze it has been involved with since its launch last year. So far, the group says it has frozen $126 million.\n\n\"Public-private partnerships are particularly effective in cryptocurrency investigations because they leverage our distinct but complementary strengths,\" Chris Janczewski, head of investigations at TRM Labs said in an email to CoinDesk.\n\n\"Law enforcement brings their traditional expertise to the investigation while the private sector is able to contribute technical capabilities which are necessary to a crypto investigation,\" he continued.\n\nSpanish authorities identified the organization through police surveillance, and were assisted by several investigative measures and Virtual Asset Service Provider (VASP) Know Your Customer (KYC) records, the release from T3 said.\n\n\"We have a team that can speak both 'crypto' and 'cop,â€™ including former law enforcement officials with extensive experience from several agencies,\" added Janczewski. \"That has allowed us to strengthen on-the-ground police work by agencies like Guardia Civil so that they can connect on-chain activity with the tangible word.\"\n\nIn a release, Paolo Ardoino, CEO of Tether, added that Tether has collaborated with more than 220 law enforcement agencies across more than 51 jurisdictions to freeze more than 2,400 addresses, amounting to nearly 2.2 billion USDT.\n\nA release from Europol noted that the organized crime syndicate was \"composed of mostly Ukrainian but also Armenian, Azerbaijani, or Kazakh nationals.\"",
    "url": "https://www.coindesk.com/policy/2025/01/30/t3-freezes-usd26-4m-linked-to-european-crime-syndicate",
    "llm_analysis": {
        "entities": {
            "persons": [
                "Chris Janczewski",
                "Paolo Ardoino"
            ],
            "positions": [
                "head of investigations at TRM Labs",
                "CEO of Tether"
            ],
            "companies": [
                "Tron",
                "Tether",
                "TRM Labs",
                "CoinDesk"
            ],
            "organizations": [
                "T3 Financial Crime Unit",
                "Spain's Guardia Civil",
                "Europol"
            ]
        },
        "cryptocurrencies": [
            "USDT"
        ],
        "impact_sentiment": "Bullish",
        "reasoning": "The news describes successful law enforcement action against criminal activity in crypto, which typically boosts market confidence by demonstrating regulatory cooperation and reducing illicit use."
    }
}