{
    "title": "Donald Trump Jr Says Crypto Is the 'Future of American Hegemony'",
    "time": "2025-02-06T22:01:00",
    "author": "Krisztian Sandor",
    "summary": "The son of the U.S. president made a surprise appearance at the Ondo Summit in New York City on Thursday.",
    "content": "Donald Trump Jr. believes crypto to be the future of American dominance, he said in a conversation at the Ondo Summit in New York City on Thursday.\n\n\"I think it's perhaps the future of American hegemony, in terms of our economic status, our economic might,\" Trump Jr. said.\n\nThe son of the U.S. president made a surprise appearance at the event after World Liberty Financial (WLF), the crypto project backed by the Trump family, bought Ondo's native cryptocurrency (ONDO) earlier today.\n\n\"We do have to create that framework in which [crypto], which I believe to be the future of finance, where we can play, where there is an understanding of what that is but also where it's not so over-regulated by people who don't know what they're talking about that you lose everything that it stands for,\" Trump Jr. said.\n\nChase Herro, co-founder of World Liberty Financial, also said that the protocol will soon launch a \"strategic reserve\" of crypto assets. \"We are big builder fans.\"\n\nWLF made headlines over the past months investing in multiple tokens including ETH, wrapped BTC, Tron's TRX, AAVE, Chainlink's LINK among other. World Liberty Financial acquired about $470,000 worth of ONDO tokens today soon after Ondo Finance announced plans to launch Ondo Chain, a layer-1 blockchain designed for tokenized assets.\n\nDuring U.S. morning hours, Trump's social media company revealed that it was looking to launch a series of exchange-traded funds (ETFs), one of them which would track the price of bitcoin\nBTC\n$104,105.54\ncalled the Truth.Fi Bitcoin Plus ETF.",
    "url": "https://www.coindesk.com/markets/2025/02/06/donald-trump-jr-says-crypto-is-the-future-of-american-hegemony",
    "llm_analysis": {
        "entities": {
            "persons": [
                "Donald Trump Jr.",
                "Chase Herro"
            ],
            "positions": [
                "co-founder",
                "U.S. president"
            ],
            "companies": [
                "World Liberty Financial",
                "Ondo Finance",
                "Trump's social media company"
            ],
            "organizations": [
                "Ondo Summit"
            ]
        },
        "cryptocurrencies": [
            "ONDO",
            "ETH",
            "BTC",
            "TRX",
            "AAVE",
            "LINK",
            "Bitcoin"
        ],
        "impact_sentiment": "Bullish",
        "reasoning": "The news describes positive statements about crypto's future from influential figures, institutional investments in multiple cryptocurrencies, and plans for new crypto-related financial products."
    }
}