{
    "title": "Crypto for Advisors: Trump: What’s Changed for Crypto?",
    "time": "2025-02-20T16:00:00",
    "author": "Beth Haddock",
    "summary": "A year ago, policy gridlock stifled crypto. Now, change is happening with the Trump administration’s stance on crypto, fueling greater acceptance and momentum.",
    "content": "As the Trump administration appears to fully embrace digital assets in the U.S., there are plenty of reasons to be optimistic about crypto’s future, but also many areas of uncertainty.\n\nIn today’s issue, Beth Haddock from Warburton Advisers takes us through the first 30 days of Trump’s term and analyzes the far-reaching impact his administration could have on the crypto industry.\n\nThen, DJ Windle from Windle Wealth answers questions you may have from the article in Ask and Expert.\n\n– Sarah Morton\n\nA year ago, skepticism and stalled policy progress stunted crypto’s growth. Trump’s election win has shifted the Overton window (referring to the change in political policies that people are willing to accept) on crypto’s acceptance, but will that lead to sustainable growth and regulatory clarity?\n\nHis January 23 Executive Order (EO) addressing crypto prioritizes \"responsible growth,\" a shift from President Biden’s 2022 EO focused on \"responsible development.\" Early actions — rescinding SAB 121, ending Operation Chokepoint 2.0, pardoning Ross Ulbricht and appointing new leaders — signal change.\n\nOne month in, progress is clear, but obstacles remain. A divided Congress, slow legislation and market speculation — seen in memecoins like $TRUMP and $MELANIA — complicate the path forward. The key question: Are we just moving past FTX, or will crypto be recognized as critical to Web3 innovation?\n\n1. Acceleration of Product Innovation\n\nThe chart above clearly illustrates the Trump administration’s early focus on leadership changes and rollbacks of enforcement-driven policies. With regulatory enforcement easing, U.S. crypto development no longer needs to wait — or move offshore.\n\nThe SEC’s Crypto 2.0 initiative, led by Commissioner Peirce, shifts from enforcement-first policies to a new Crypto Taskforce. Meanwhile, the President’s Working Group on Digital Asset Markets, chaired by crypto advocate David Sacks, signals a more supportive stance. These shifts create space for innovation, allowing blockchain to prove its value before regulations catch up.\n\nKey areas for progress include stablecoin regulation, clearer digital asset custody requirements, hybrid TradFi-crypto products (such as expected Solana and ETH ETFs) and global payments advancements through partnerships like those with X Money and Visa. Resolving complex policy priorities will take time, as reflected in a16z’s 11 priorities and the Crypto Bar’s open letter, highlighting the breadth of influential voices.\n\nAs adoption grows, the network effect of successful crypto products will push for consensus-driven regulation. But without meaningful legislative action, the industry risks a return to uncertainty when Washington’s leadership inevitably shifts again.\n\n2. Speculation vs. Sustainable Growth\n\nAmid all this optimism, crypto still struggles to establish credibility and prove itself as a force for responsible innovation. The opportunity to revolutionize finance is here — but is market speculation part of the growth or is it hindering sustainable growth?\n\nMemecoins like $TRUMP and $MELANIA surged just before the inauguration, reflecting demand for high-risk, culturally driven assets, while also raising regulatory concerns about volatility and integrity. The class action lawsuit against pump.fun underscores skepticism of growth untethered to sustainable utility.\n\nTo maintain credibility, crypto must distinguish real-world and potential wealth creation applications from speculative assets. Fraud and misrepresentation remain illegal, whether in memecoins, penny stocks or collectibles. As the market evolves, businesses and investors must prioritize due diligence to separate hype from lasting potential.\n\n3. The Urgent Need for Regulatory Clarity\n\nDespite leadership changes, there remains an urgent need for clear, enforceable crypto regulation. Key unresolved issues include:\n\nWith crypto-friendly leaders now at the SEC and CFTC, regulatory progress is likely, but legislative action will take time. While Congress is considering proposals like the GENIUS Act, the STABLE Act, and new rules for market structure, pragmatic change isn’t guaranteed this year.\n\nFor now, the industry must keep shifting the Overton window toward recognizing crypto’s role in U.S. tech leadership, public policy and economic security. Until comprehensive laws emerge, regulatory leadership — seen with the CFTC pilot program and recent Federal Reserve speech — must guide a stable path for growth.\n\nThis year is pivotal — not just because toxic policies are fading and leadership has shifted, but because momentum is driving Web3 and blockchain forward.\n\nThe goal isn’t just \"responsible growth\" but sustainable growth anchored in regulatory clarity. If the industry balances innovation with strong protections against fraud and theft, crypto’s resilience and credibility will be strengthened. With tech-neutral regulations, the U.S. won’t just lead in crypto and AI policy — we’ll also be ready for whatever else is next, from quantum computing to future breakthroughs. Sustainable innovation matters because technological progress is inevitable.\n\n-Beth Haddock, managing partner and founder, Warburton Advisers\n\nQ: Who is Ross Ulbricht?\n\nA: Ross Ulbricht created Silk Road, an early bitcoin-powered marketplace that demonstrated crypto’s potential for decentralized commerce — both legally and illegally. His life sentence became a rallying cry in the crypto community, with many arguing it was excessive and highlighting broader debates on financial privacy and government control. His recent pardon has reignited discussions on justice reform and crypto’s role in the future of digital trade.\n\nQ: What are the risks of memecoins?\n\nA: Memecoins like $TRUMP and $MELANIA are highly speculative, with prices driven more by social media hype than real utility. While they can generate quick profits, they also carry extreme volatility and risks of manipulation. Many lack long-term viability, so investors should approach them with caution and avoid putting more in them than they can afford to lose.\n\nQ: How could state bitcoin investments impact adoption?\n\nA: If states allocate reserves to bitcoin, it could legitimize crypto as a store of value, encouraging institutional investors and policymakers to take it more seriously. This could accelerate regulatory clarity, enhance calls for clearer tax guidelines and integrate bitcoin into broader financial infrastructure, helping solidify its role in the economy.\n\n-DJ Windle, founder and portfolio manager, Windle Wealth",
    "url": "https://www.coindesk.com/coindesk-indices/2025/02/19/crypto-for-advisors-trump-what-s-changed-for-crypto",
    "llm_analysis": {
        "entities": {
            "persons": [
                "Trump",
                "Beth Haddock",
                "DJ Windle",
                "Sarah Morton",
                "Ross Ulbricht",
                "Commissioner Peirce",
                "David Sacks",
                "Biden"
            ],
            "positions": [
                "managing partner and founder",
                "founder and portfolio manager",
                "Commissioner",
                "chair"
            ],
            "companies": [
                "Warburton Advisers",
                "Windle Wealth",
                "a16z",
                "X Money",
                "Visa",
                "pump.fun",
                "FTX",
                "Silk Road"
            ],
            "organizations": [
                "Trump administration",
                "SEC",
                "CFTC",
                "President's Working Group on Digital Asset Markets",
                "Crypto Taskforce",
                "Congress",
                "Federal Reserve"
            ]
        },
        "cryptocurrencies": [
            "Bitcoin",
            "BTC",
            "Ethereum",
            "ETH",
            "Solana",
            "$TRUMP",
            "$MELANIA"
        ],
        "impact_sentiment": "Bullish",
        "reasoning": "The news describes the Trump administration's crypto-friendly policies, regulatory easing, and positive momentum as creating optimism about crypto's future with greater acceptance and innovation."
    }
}