{
    "title": "CleanSpark Ditches Bitcoin 'HODL' Strategy to Stop Dilution Via Equity Raise",
    "time": "2025-04-15T14:02:00",
    "author": "Jamie Crawley",
    "summary": "CleanSpark's holdings now exceed 12,000 BTC, worth just over $1 billion at current prices.",
    "content": "Bitcoin miner CleanSpark (CLSK) is moving away from its strategy of HODLing 100% of the BTC it mines.\n\nThe Henderson, Nevada-based company said it is returning to selling a portion of the bitcoin mined to support its operations in an announcement on Tuesday.\n\n\"While we remain committed to bitcoin as a long-term, hardened asset, we believe a more effective way to increase shareholder value is through a balanced approach between monetizing new production and building long-term holdings,\" CEO Zach Bradford said.\n\nCleanSpark's holdings now exceed 12,000 BTC, worth just over $1 billion at current prices.\n\nThe company has also increased its credit facility with Coinbase Prime (COIN) to $200 million, pursuing a strategy of funding its operations without having to sell equity. CleanSpark, which has 40.2 exahash per second (EH/s) mining power, is looking to expand it to 50 EH/s.\n\n\"As part of this balanced approach, we intend to further build out our diversified capital stack. In today's market environment, we view the debt markets as the most efficient and responsible path to support accretive growth, and our strong balance sheet positions us to take full advantage of that opportunity,\" Bradford added.\n\nCLSK shares rose just over 1% before paring their gains in early trading on Tuesday, outperforming the broader BTC mining sector, as measured by the CoinShares Bitcoin Miners ETF (WGMI), which fell more than.",
    "url": "https://www.coindesk.com/business/2025/04/15/cleanspark-ditches-bitcoin-hodl-strategy-to-stop-dilution-via-equity-raise",
    "llm_analysis": {
        "entities": {
            "persons": [
                "Zach Bradford"
            ],
            "positions": [
                "CEO"
            ],
            "companies": [
                "CleanSpark",
                "Coinbase Prime",
                "CLSK"
            ],
            "organizations": [
                "CoinShares Bitcoin Miners ETF"
            ]
        },
        "cryptocurrencies": [
            "Bitcoin",
            "BTC"
        ],
        "impact_sentiment": "Bullish",
        "reasoning": "The news describes CleanSpark's strategic shift to fund operations through bitcoin sales and debt rather than equity dilution, which resulted in their stock outperforming the mining sector and indicates market confidence in their approach."
    }
}