{
    "title": "Tether Boosts Stake in $1.12B Agricultural Firm Adecoagro to 70%",
    "time": "2025-03-27T13:07:00",
    "author": "Jamie Crawley",
    "summary": "AGRO shares jumped over 7% to $11.95 in pre-market trading following the announcement",
    "content": "Tether, issuer of $144 billion dollar stablecoin USDT, has boosted its stake in Latin American agricultural firm Adecoagro (AGRO).\n\nThe $12.41 per share offer, which is subject to certain closing conditions, would take Tether's stake in Adecoagro from 51% to 70%, according to an announcement on Thursday.\n\nAGRO shares jumped over 7% to $11.95 in pre-market trading following the announcement.\n\nAdecoagro's business is focused on sugar, ethanol, dairy and crop production Argentina, Brazil, and Uruguay. It owns 210,400 hectares of farmland and several industrial facilities across these countries.\n\nThe company has a market cap of just under $1.12 billion.\n\nTether views its Adecoagro's investment as one in the safe haven of land that complements its holdings in bitcoin\nBTC\n$107,226.55\nand gold.\n\n\"Our investment aligns with Tether's broader strategy to back infrastructure, technology, and businesses that advance economic freedom and resilience,\" Tether CEO Paolo Ardoino said in Thursday's announcement.\n\nTether is also increasing its exposure to the entertainment industry, acquiring a 30.4% stake in Italian media company Be Water for 10 million euros ($10.8 million).\n\nThis investment follows Tether's announcement last month of taking a minority stake in Ardoino's favorite team Juventus FC, arguably the largest soccer club in Italy.",
    "url": "https://www.coindesk.com/business/2025/03/27/tether-boosts-stake-in-usd1-12b-agricultural-firm-adecoagro-to-70",
    "llm_analysis": {
        "entities": {
            "persons": [
                "Paolo Ardoino"
            ],
            "positions": [
                "Tether CEO"
            ],
            "companies": [
                "Tether",
                "Adecoagro",
                "Be Water",
                "Juventus FC"
            ],
            "organizations": []
        },
        "cryptocurrencies": [
            "USDT",
            "BTC",
            "Bitcoin"
        ],
        "impact_sentiment": "Bullish",
        "reasoning": "The news shows Tether expanding strategic investments and describes agricultural investments as complementing cryptocurrency holdings, indicating market confidence and positive expansion."
    }
}