{
    "title": "China, Germany Fire Fiscal Rockets as U.S. Looks to Cut Spending. What Does it Mean for Bitcoin?",
    "time": "2025-03-05T14:42:00",
    "author": "Omkar Godbole",
    "summary": "China and Germany's shift in fiscal policy might calm crypto market nerves.",
    "content": "Just as anabolic steroids are to bodybuilders, fiscal and monetary stimuli have been the lifeline for markets and the economy. Over the decades, nation-states have relied heavily on these fiscal injections to buff up markets and respective economies.\n\nNow, to the delight of BTC and risk asset bulls, China, the world's second-largest economy, and European Union's heavyweight Germany have announced fresh fiscal bazookas. That might help calm crypto and traditional market nerves about the negative impact of the Trump administration's plan to reduce spending and the Presidentâ€™s tariffs policies.\n\nThe National People's Congress opened in Beijing today, targeting 5% GDP growth for 2025 while raising the fiscal deficit target to 4% of GDP, a full 100 basis points higher than the previous year's 2% target.\n\n\"An increasingly complex and severe external environment may exert a greater impact on China in areas such as trade, science, and technology,\" Premier Li Qiang said in his speech.\n\nNotably, the plan showed that boosting domestic demand and consumption has become a top priority, in line with Beijing's long-term plan to be a more consumer-driven growth model than an investment-driven one.\n\nThe decision to maintain the 5% target indicates that \"policymakers continue to have confidence in stabilising growth despite stronger external headwinds,\" ING said.\n\nMeanwhile, early this week, Germany said it would unlock hundreds of billions of euros for defence and infrastructure investments, abandoning its famed fiscal rectitude.\n\n\"The massive shift in fiscal policy likely gives the struggling German economy a shot in the arm. A jump in defence spending might provide a cyclical boost, the proposed infrastructure package could deliver notable potential output gains in the long run,\" Bloomberg economists said.\n\nAsian and European equity markets rallied early today, cheering the fiscal bazooka from China and Germany. Bitcoin, too, has risen nearly 3% to $90,000, having defended the 200-day average Tuesday.\n\nAside from potentially compensating for any fiscal tightening in the U.S., China and Germany's fiscal plan could also work its magic through the FX channel by putting the dollar under pressure.\n\nWhen a country increases its borrowing, it typically signifies that bond supply will rise, placing downward pressure on bond prices and driving yields higher. This, in turn, enhances the appeal of the domestic currency.\n\nThat's already happening. Germany's 10-year bond yield has jumped 36 basis points to 2.73% since Feb. 25, reaching the highest since November 2023, according to charting platform TradingView. As such, the spread between yields on the 10-year U.S.-German government bond yields has tanked to 1.49% in the USD-negative manner, hitting the lowest since September and down significantly from the high of 2.31% in December.\n\nThe narrowing of the yield spread has lifted the EUR/USD, the most liquid FX pair, spurring a broad-based USD selling and pushing the dollar index below 105.00 for the first time since November.\n\nWeakness in the greenback, a global reserve, tends to ease financial conditions worldwide, spurring increased risk-taking in financial markets.",
    "url": "https://www.coindesk.com/business/2025/03/05/china-germany-fire-fiscal-rockets-as-u-s-looks-to-cut-spending-what-does-it-mean-for-bitcoin",
    "llm_analysis": {
        "entities": {
            "persons": [
                "Li Qiang"
            ],
            "positions": [
                "Premier"
            ],
            "companies": [
                "ING",
                "Bloomberg",
                "TradingView"
            ],
            "organizations": [
                "China",
                "Germany",
                "U.S.",
                "European Union",
                "National People's Congress",
                "Trump administration"
            ]
        },
        "cryptocurrencies": [
            "Bitcoin",
            "BTC"
        ],
        "impact_sentiment": "Bullish",
        "reasoning": "The news states that China and Germany's fiscal stimulus 'might help calm crypto and traditional market nerves' and specifically mentions Bitcoin rising nearly 3% to $90,000 while defending key technical levels."
    }
}