{
    "title": "Crypto Daybook Americas: PEPE Signals Altcoin Frenzy as Rampant Ether Outpaces Bitcoin",
    "time": "2025-05-09T11:15:00",
    "author": "Omkar Godbole",
    "summary": "Your day-ahead look for May 9, 2025",
    "content": "By Omkar Godbole (All times ET unless indicated otherwise)\n\nAs the crypto rally gathers pace, ether has widened its lead over bitcoin in terms of volatility expectations, signaling relatively greater action not just in the second-largest cryptocurrency, but in the broader digital asset market as a whole.\n\nDeribit's ether implied volatility index (ETH DVOL), which represents the 30-day expected price turbulence, has shot up 11% to an annualized 7% this week while the bitcoin equivalent, BTC DVOL, held steady near multimonth lows around 45%, according to data source TradingView.\n\nThe divergence has widened the spread between the two to 27%, the most in at least two years. Clearly, traders are anticipating greater volatility in ETH and the broader altcoin market.\n\nAccording to some observers, ETH has turned deflationary because the Pectra upgrade implemented this week has boosted on-chain activity and led to over 38,000 ETH burned or destroyed in the past 24 hours. Some market participants are buying higher strike ETH calls on Deribit in anticipation of continued price gains.\n\nWe could be on the verge of an altcoin season, as the BTC dominance rate looks to end its five-month-long uptrend. (Check out Technical Analysis).\n\nIn key news, American fast-food chain Steak â€˜n Shake said Thursday it will begin accepting BTC as a payment mode at all U.S. locations starting May 16, allowing its 100 million customers to shop with the world's biggest digital-asset token.\n\nT-Rex, the Web3 consumer entertainment platform, which is backed by Portal Ventures, North Island Ventures, Framework Ventures and Arbitrum Gaming Ventures, raised $17 million in pre-seed financing.\n\nFinally, just in case you missed it, cryptocurrency exchange Coinbase agreed to buy the world's largest crypto options exchange, Deribit, for $2.9 billion in cash and shares in the crypto industry's largest ever M&A deal. Deribit controls over 80% of the activity, meaning Coinbase will be able to offer a full suite of spot and derivative products, boosting liquidity on the platform. Stay alert!\n\nCoinDesk's Consensus is taking place in Toronto on May 14-16. Use code DAYBOOK and save 15% on passes.\n\nBy Shaurya Malwa\n\nSpot BTC ETFs:\n\nSpot ETH ETFs\n\nSource: Farside Investors",
    "url": "https://www.coindesk.com/daybook-us/2025/05/09/crypto-daybook-americas-pepe-signals-altcoin-frenzy-as-rampant-ether-outpaces-bitcoin",
    "llm_analysis": {
        "entities": {
            "persons": [
                "Omkar Godbole",
                "Shaurya Malwa"
            ],
            "positions": [],
            "companies": [
                "Steak 'n Shake",
                "T-Rex",
                "Portal Ventures",
                "North Island Ventures",
                "Framework Ventures",
                "Arbitrum Gaming Ventures",
                "Coinbase",
                "Deribit"
            ],
            "organizations": [
                "CoinDesk",
                "Farside Investors"
            ]
        },
        "cryptocurrencies": [
            "PEPE",
            "Ether",
            "ETH",
            "Bitcoin",
            "BTC"
        ],
        "impact_sentiment": "Bullish",
        "reasoning": "The news describes a crypto rally gathering pace, ether widening its lead over bitcoin, anticipation of greater volatility and price gains, potential altcoin season, and major corporate adoption and M&A activity."
    }
}