{
    "title": "Bitcoin Surges to $109K, Hits Record High Ahead of Donald Trump's Inauguration",
    "time": "2025-01-20T07:21:00",
    "author": "Shaurya Malwa",
    "summary": "Bitcoin (BTC) zoomed to a record level above $109,000 during the Asian trading hours on Monday ahead of Republican Donald Trump's scheduled inauguration later in the day.",
    "content": "Bitcoin\nBTC\n$104,608.94\nzoomed to a record level above $109,000 during the Asian trading hours on Monday ahead of Republican Donald Trump's scheduled inauguration later in the day. The largest cryptocurrency touched $109,333 on Binance.\n\nTrump mentioned the asset's record performance in a Sunday speech alongside gains in the broader U.S. stock market.\n\n\"Since the election, the stock market has surged and small business optimism has soared a record 41 points to a 39-year high. Bitcoin has shattered one record high after another,\" Trump said.\n\nBTC reversed losses from earlier in the day when it fell to nearly $100,000 from a high over $102,000 on Sunday as first lady Melania Trump issued a memecoin, drawing liquidity away from major assets.\n\nTrump has been vocal about his support for cryptocurrencies during his campaign. Promises like making the U.S. the \"crypto capital of the planet\" and creating a \"strategic national bitcoin reserve\" have fueled investor optimism.\n\n\"Bitcoin reached $108K while other cryptocurrencies have rapidly pumped on the eve of the US presidential inauguration, with hopes that new policies and regulators will send the price of BTC much further this year as the US economy continues to show strength in the long term,\" Ben El-Baz, Managing Director of HashKey Global, told CoinDesk in a Telegram message.\n\n\"The forward momentum has been further accelerated by the launch of the TRUMP and MELANIA memecoins which have attracted more retail users, and hopes that Trump will prioritize and reaffirm his commitment to the crypto industry.\"\n\n\"Designating crypto as a national priority and launching TRUMP coin over the past few days have been strong, positive signals. As the main bellwether for the industry, Bitcoin's surge was expected and is likely to continue through the week,\" Jeff Mei, COO at BTSE, said in a Telegram message.\n\nYear-end bitcoin targets range from $185,000 to as high as $250,000, as CoinDesk previously reported.\n\nMeanwhile, bitcoin dominance has started to trend higher and is now approaching 60%, the highest level since Dec. 20. The spread between the two largest cryptocurrencies, bitcoin and ether\nETH\n$3,495.36\n, continues to widen, with a $1.75 trillion market cap differential â€” the largest difference ever recorded.",
    "url": "https://www.coindesk.com/markets/2025/01/20/bitcoin-surges-to-109-k-hits-record-high-ahead-of-donald-trumps-inauguration",
    "llm_analysis": {
        "entities": {
            "persons": [
                "Donald Trump",
                "Melania Trump",
                "Ben El-Baz",
                "Jeff Mei"
            ],
            "positions": [
                "Managing Director",
                "COO"
            ],
            "companies": [
                "Binance",
                "HashKey Global",
                "BTSE"
            ],
            "organizations": [
                "CoinDesk"
            ]
        },
        "cryptocurrencies": [
            "Bitcoin",
            "BTC",
            "ETH",
            "TRUMP",
            "MELANIA"
        ],
        "impact_sentiment": "Bullish",
        "reasoning": "The news describes Bitcoin surging to record highs, positive policy expectations from Trump's inauguration, and analyst predictions of continued price increases."
    }
}