{
    "title": "Crypto Ecosystem Growth Slowed in January Even as Total Market Cap Rose, JPMorgan Says",
    "time": "2025-02-11T14:56:00",
    "author": "Will Canny",
    "summary": "Total crypto market cap increased 8% to about $3.4 trillion last month, the report said.",
    "content": "Crypto ecosystem growth slowed in January, with total trading volume dropping 24%, Wall Street bank JPMorgan (JPM) said in a research report Tuesday citing TradingView data.\n\nStill, the activity is double the level before the U.S. election in November and the total market cap increased 8% to roughly $3.4 trillion, the report said. The market cap growth was concentrated in bitcoin (BTC), solana (SOL) and XRP, while \"declines in average daily volume (ADV) were broad-based across the ecosystem,\" the bank said.\n\n\"We think the election was a catalyst for sure, and activity and token price levels are finding their equilibrium in the post-election period,\" analysts led by Kenneth Worthington wrote.\n\nDecentralized finance (DeFi) and non-fungible tokens (NFTs) fared worse on a monthly basis the report said, with a larger deterioration across a number of metrics.\n\nThere has been some progress on the regulatory front.\n\nThe new Trump administration established a new crypto taskforce and SAB 121, a controversial accounting rule, was rescinded, JPMorgan said.\n\nRead more: Equities-Crypto Relationship Is Likely to Weaken in the Long Term, Citi Says",
    "url": "https://www.coindesk.com/markets/2025/02/11/crypto-ecosystem-growth-slowed-in-january-even-as-total-market-cap-rose-jpmorgan-says",
    "llm_analysis": {
        "entities": {
            "persons": [
                "Kenneth Worthington"
            ],
            "positions": [
                "analysts"
            ],
            "companies": [
                "JPMorgan",
                "Citi"
            ],
            "organizations": [
                "Wall Street bank",
                "TradingView",
                "Trump administration",
                "DeFi",
                "NFTs"
            ]
        },
        "cryptocurrencies": [
            "bitcoin",
            "BTC",
            "solana",
            "SOL",
            "XRP"
        ],
        "impact_sentiment": "Consolidation",
        "reasoning": "The news reports mixed signals with market cap growth but declining trading volume and ecosystem slowdown, indicating the market is finding equilibrium rather than showing clear directional momentum."
    }
}