{
    "title": "Ripple, Galaxy Execs Loaned $160M to Moonpay So That They Could Support TRUMP Memecoin Launch",
    "time": "2025-02-12T10:33:00",
    "author": "Shaurya Malwa",
    "summary": "The massive demand came on a Saturday, when MoonPay‚Äôs fiat accounts were inaccessible due to the weekend with a public holiday on the following Monday for the swearing-in.",
    "content": "Loans from Galaxy and Ripple played a pivotal role in helping crypto exchange MoonPay handle the demand stemming from the launch of Donald Trump‚Äôs official memecoin after its Jan.18 issuance, a new podcast reveals.\n\nRipple Brad Garlinghouse and Mike Novogratz lent Moonpay $160M to launch the $TRUMP Token üëÄ pic.twitter.com/jaA5rl9QGz\n\nTRUMP launched days before the President's swearing-in ceremony. The token launch was a surprise move that made him the first-ever president to be directly related to a memecoin. The token was launched on Moonshot, for which MoonPay is the exclusive crypto payments provider.\n\nThe token's market capitalization zoomed from nearly $200 million at issuance to over $10 billion within 48 hours ‚Äî bagging spot and futures listings across exchanges and over $20 billion in trading volumes over two days.\n\nThe massive demand came on a Saturday, when MoonPay‚Äôs fiat accounts were inaccessible due to the weekend with a public holiday on the following Monday for the swearing-in.\n\nThe situation meant MoonPay could not readily access over $100 million in liquidity required to meet TRUMP‚Äôs trading demand ‚Äî leaving a short term loan as the only option to ensure business went as usual.\n\nMoonPay president Keith Grossman, along with CEO Ivan Soto-Wright and CFO Mouna Siala, estimated the company needed around $100 million worth of USD Coin stablecoin.\n\nThat‚Äôs when Novogratz was contacted for a loan. After securing an agreement, MoonPay quickly prepared the necessary documentation and verified their ability to repay after vetting with a BlackRock executive, where MoonPay held its reserve funds.\n\nHowever, demand for the TRUMP token continued to escalate and first lady Melania Trump‚Äôs MELANIA tokens were, too, launched, leading to the $100 million being insufficient to meet liquidity requirements. That pushed MoonPay to seek another $60 million in funds. Grossman then connected with Ripple‚Äôs Garlinghouse, stating he had ‚Äúunderestimated the demand of this Trump token.‚Äù\n\nRipple contributed the additional $60 million needed after a thorough vetting, including a pledge of MoonPay‚Äôs Soto-Wright for his entire personal assets. MoonPay further had to prove there were no liens on its reserve capital.\n\nMoonPay repaid all loans in full on Jan.21, a Tuesday after the long weekend when it could finally access its reserve funds. The company onboarded 750,000 new users that week.\n\nPrices of TRUMP, despite its blockbuster launch, are down 79% since its Jan. 19 peak.",
    "url": "https://www.coindesk.com/markets/2025/02/12/ripple-galaxy-execs-usd160m-loan-helped-moonpay-handle-trump-memecoin-launch",
    "llm_analysis": {
        "entities": {
            "persons": [
                "Brad Garlinghouse",
                "Mike Novogratz",
                "Donald Trump",
                "Keith Grossman",
                "Ivan Soto-Wright",
                "Mouna Siala",
                "Melania Trump"
            ],
            "positions": [
                "president",
                "CEO",
                "CFO",
                "first lady"
            ],
            "companies": [
                "Ripple",
                "Galaxy",
                "MoonPay",
                "BlackRock",
                "Moonshot"
            ],
            "organizations": []
        },
        "cryptocurrencies": [
            "TRUMP",
            "MELANIA",
            "USD Coin"
        ],
        "impact_sentiment": "Bullish",
        "reasoning": "The massive demand for TRUMP token with market cap zooming from $200M to over $10B and $20B in trading volumes indicates strong market enthusiasm and institutional support."
    }
}