{
    "title": "Genesis Files Suits Against DCG to Recover Billions Worth of Allegedly Fraudulent Transfers",
    "summary": "DCG, CEO Barry Silbert and others withdrew billions of dollars from the company they knew was failing while keeping customers in the dark, according to the lawsuits.",
    "time": "2025-05-20T16:43:00",
    "author": "Camomile Shumba",
    "content": "Crypto lender Genesis and its subsidiaries filed two lawsuits against its parent company, Digital Currency Group (DCG), DCG CEO Barry Silbert and other executives, seeking to recover what it called fraudulent transfers of crypto worth billions of dollars.\n\nIn total, the estate of the bankrupt company and its creditors are seeking $3.2 billion across the two lawsuits. It is seeking to recover $2.2 billion in a suit filed in the Court of Chancery of the State of Delaware and more than $1 billion in a suit at the Bankruptcy Court for the Southern District of New York.\n\nThe New York filing says money was withdrawn from Genesis to repay DCG, Silbert, affiliates and other insiders in the year that led up to Genesis filing for Chapter 11 even though the company was insolvent.\n\nThey \"knew through their close relationship with Genesis that its business was on the brink of collapse\" and took the opportunity to withdraw all their assets and recover 100% of crypto and dollar loans made to the platform while members of the public were \"kept in the dark,\" the suit alleges.\n\nGenesis suspended withdrawals in November 2022 and went into bankruptcy the following year.\n\n\"Silbert and his cronies recklessly operated, exploited, and then bankrupted Genesis following a spectacular campaign of fraud and self-dealing,\" the Delaware filing alleges.\n\nIts creditors are still short $2.2 billion worth of crypto assets including bitcoin\nBTC\n$102,205.43\n, ether\nETH\n$3,340.48\nand other tokens, the filing said.\n\nAlongside seeking an award of damages, Genesis wants an equitable trust over any assets the \"defendants improperly took or converted during their tenure as managers, officers, directors,\" the filing said.\n\nâ€œThese baseless lawsuits recycle the same tired, two-year old claims in an opportunistic attempt by sophisticated investors to extract additional value from DCG,\" a spokesperson for the company said. \"We worked in good faith with a wide range of stakeholders to try to achieve a comprehensive resolution of the DCG-related aspects of the Genesis bankruptcy. We will vigorously defend ourselves against these spurious claims.\"\n\nCORRECT (May 23, 14:06 UTC): Corrects the second bullet point, second paragraph to say the claim is made by the Genesis estate.",
    "url": "https://www.coindesk.com/policy/2025/05/20/genesis-files-suits-against-dcg-to-recover-billions-worth-of-allegedly-fraudulent-transfers",
    "llm_analysis": {
        "entities": {
            "persons": [
                "Barry Silbert"
            ],
            "positions": [
                "CEO"
            ],
            "companies": [
                "Genesis",
                "Digital Currency Group (DCG)"
            ],
            "organizations": [
                "Court of Chancery of the State of Delaware",
                "Bankruptcy Court for the Southern District of New York"
            ]
        },
        "cryptocurrencies": [
            "bitcoin",
            "BTC",
            "ether",
            "ETH"
        ],
        "impact_sentiment": "Bearish",
        "reasoning": "The news describes billions in alleged fraudulent transfers, bankruptcy proceedings, and creditors being short $2.2 billion in crypto assets, indicating significant negative developments in the cryptocurrency lending sector."
    }
}