{
    "title": "OpenAI's Reported $340B Valuation Could Bode Well for AI-Linked Crypto",
    "time": "2025-01-30T20:52:00",
    "author": "Aoyon Ashraf",
    "summary": "Wall Street Journal reported that OpenAI is in talks to raise new $40 billion funding, at a valuation of $340 billion.",
    "content": "ChatGPT maker OpenAI is in early-stage talks with investors to raise $40 billion in a fresh funding round, WSJ reported, citing people familiar with the matter. The new financing would value the artificial intelligence (AI) giant at $340 billion.\n\nPreviously, OpenAI was valued at $157 billion when it raised $6.6 billion in October, according to the report. For the new round, SoftBank is said to be the lead investor supplying funding between $15 billion and $25 billion, the story continued.\n\nThis could bode well for AI-linked cryptocurrencies, as OpenAI almost doubling its valuation would bring back some confidence into the sector after competitor DeepSeek's rise took some froth out of the industry.\n\nAccording to CoinGecko data, some of the large-cap AI-linked tokens include NEAR, ICP, TAO, RENDER, FET, GRT, and AI16Z.\n\nRead more: AI Tokens Are the Real Losers of the DeepSeek Revolution\n\nChatGPT maker OpenAI is in early-stage talks with investors to raise $40 billion in a fresh funding round, WSJ reported, citing people familiar with the matter. The new financing would value the artificial intelligence (AI) giant at $340 billion.\n\nPreviously, OpenAI was valued at $157 billion when it raised $6.6 billion in October, according to the report. For the new round, SoftBank is said to be the lead investor supplying funding between $15 billion and $25 billion, the story continued.\n\nThis could bode well for AI-linked cryptocurrencies, as OpenAI almost doubling its valuation would bring back some confidence into the sector after competitor DeepSeek's rise took some froth out of the industry.\n\nAccording to CoinGecko data, some of the large-cap AI-linked tokens include NEAR, ICP, TAO, RENDER, FET, GRT, and AI16Z.\n\nRead more: AI Tokens Are the Real Losers of the DeepSeek Revolution\n\nMore For You\n\nOwlTing: Stablecoin Infrastructure for the Future\n\nStablecoin payment volumes have grown to $19.4B year-to-date in 2025. OwlTing aims to capture this market by developing payment infrastructure that processes transactions in seconds for fractions of a cent.\n\nRipple Acquires Crypto Wallet Firm Palisade to Expand Institutional Payments Business\n\nWith the acquisition, Ripple aims to provide quickly-deployable wallets to boost fintech and corporate crypto payments, president Monica Long said in an interview.\n\nWhat to know:",
    "url": "https://www.coindesk.com/business/2025/01/30/openai-s-reported-usd340b-valuation-could-bode-well-for-ai-linked-crypto",
    "llm_analysis": {
        "entities": {
            "persons": [
                "Monica Long"
            ],
            "positions": [
                "president"
            ],
            "companies": [
                "OpenAI",
                "SoftBank",
                "Ripple",
                "Palisade",
                "OwlTing"
            ],
            "organizations": [
                "Wall Street Journal",
                "CoinGecko"
            ]
        },
        "cryptocurrencies": [
            "NEAR",
            "ICP",
            "TAO",
            "RENDER",
            "FET",
            "GRT",
            "AI16Z"
        ],
        "impact_sentiment": "Bullish",
        "reasoning": "The news states that OpenAI's valuation increase 'could bode well for AI-linked cryptocurrencies' and 'would bring back some confidence into the sector'."
    }
}