{
    "title": "CoinDesk Indices Launches CoinDesk 100, Memecoin Index in Industry Boost",
    "time": "2025-02-20T01:00:00",
    "author": "Shaurya Malwa",
    "summary": "Crypto exchange Bullish has listed perpetual futures on both indices, allowing traders to gain exposure to these benchmarks with deep liquidity and around-the-clock trading.",
    "content": "HONG KONG - CoinDesk Indices launched two index products tracking the price gyrations of memecoins and the top hundred tokens by market capitalization, meeting demand from institutional and professional investors who seek upside in different crypto sectors, the firm announced at Consensus Hong Kong.\n\nThe CoinDesk Memecoin Index will track the largest fifty memecoins by market capitalization — a list that includes\nDOGE\n$0.1659\n,\nSHIB\n$0.0₅9084\n,\nFLOKI\n$0.0₄5894\n, among others — while the CoinDesk 100 serves as a single benchmark for the top hundred tokens by market cap.\n\n“CoinDesk Memecoin Index responds to traders' need for liquidity and volatility while the CoinDesk 100 provides one-stop access to the most liquid tokens,” said Chris Tyrer, VP, head of institutional at Bullish.\n\n“We are thrilled to continue providing our clients access to the broader digital asset landscape, complementing these indices with our robust regulatory framework,\" he added.\n\nThe memecoin index is equal-weighted and will be rebalanced monthly, ensuring the representation of emerging and established tokens. Similarly, the CoinDesk 100 Index is market cap-weighted and provides a single reference point for structured products, ETFs, and risk management strategies.\n\nCrypto exchange Bullish has listed perpetual futures on both indices, allowing traders to gain exposure to these benchmarks with deep liquidity and around-the-clock trading.\n\nThis launch builds on the success of the CoinDesk 20 and CoinDesk 80 perpetuals, which have collectively driven over $13.5 billion in volume, with the CoinDesk 80 index perpetual future trading millions daily since January 2025.",
    "url": "https://www.coindesk.com/markets/2025/02/20/coindesk-indices-launches-coindesk-100-memecoin-index-in-industry-boost",
    "llm_analysis": {
        "entities": {
            "persons": [
                "Chris Tyrer"
            ],
            "positions": [
                "VP, head of institutional"
            ],
            "companies": [
                "CoinDesk Indices",
                "Bullish"
            ],
            "organizations": []
        },
        "cryptocurrencies": [
            "DOGE",
            "SHIB",
            "FLOKI"
        ],
        "impact_sentiment": "Bullish",
        "reasoning": "The launch of new indices and perpetual futures products provides institutional access and meets investor demand for different crypto sectors, indicating market growth and confidence."
    }
}