{
    "title": "Trump-Family Backed World Liberty Financial Starts Token Reserve for Crypto Investment",
    "time": "2025-02-12T11:27:00",
    "author": "Parikshit Mishra",
    "summary": "The protocol has already accumulated tokens of various networks.",
    "content": "The Trump-family backed World Liberty Financial launched its token reserve to back various crypto ecosystems, the decentralized finance (DeFi) protocol said in an X post on Wednesday.\n\nWorld Liberty said it will diversify its token holdings and engage with traditional finance firms to invest their tokenized assets into the reserve.\n\nThe protocol did not disclose any details on which tokens the reserve would invest in, but did say it will have a particular focus on DeFi.\n\nLast week, World Liberty Financial co-founder Chase Herro said the protocol will start a \"strategic reserve\" of crypto assets.\n\nIt has already accumulated various tokens, including TRON's TRX, USDC, Ether\nETH\n$3,643.96\nand staked ETH, as well as MOVE and ONDO tokens, according to data from Arkham Intelligence.",
    "url": "https://www.coindesk.com/business/2025/02/12/trump-family-backed-world-liberty-financial-starts-token-reserve-for-crypto-investment",
    "llm_analysis": {
        "entities": {
            "persons": [
                "Trump",
                "Chase Herro"
            ],
            "positions": [
                "co-founder"
            ],
            "companies": [
                "World Liberty Financial"
            ],
            "organizations": [
                "Arkham Intelligence"
            ]
        },
        "cryptocurrencies": [
            "TRON",
            "TRX",
            "USDC",
            "Ether",
            "ETH",
            "staked ETH",
            "MOVE",
            "ONDO"
        ],
        "impact_sentiment": "Bullish",
        "reasoning": "The launch of a token reserve by a Trump-family backed entity to invest in various crypto ecosystems and DeFi indicates institutional confidence and potential market inflows."
    }
}