{
    "title": "Trump-Backed World Liberty Financial to Acquire TRX for its Treasury: Source",
    "time": "2025-01-18T02:05:00",
    "author": "Oliver Knight",
    "summary": "A Tron delegation will attend Trump's inauguration on Monday.",
    "content": "World Liberty Financial, the crypto project backed by the family of U.S. President-elect Donald Trump, plans to acquire\nTRX\n$0.2837\ntokens for its treasury, according to a person familiar with the matter.\n\nThe prospective move would deepen World Liberty Financial's close ties to the Tron empire. Its founder Justin Sun already advises Trump's crypto project. He's also single-largest holder of its WLFI token, having bought $30 million in November.\n\nIt's not clear how much TRX World Liberty plans to add to its reserve of cryptocurrencies. World Liberty's raised $90 million from sales of WLFI. Its previously parked seven-figure sums in AAVE and LINK, tokens issued by projects World Liberty's partnered with.\n\nTrump is officially the \"chief crypto advocate\" of World Liberty Financial, which plans to offer crypto-financial services to the masses. His imminent return to the White House is being heralded as a watershed moment for the crypto industry.\n\nTron's along for the ride. A delegation from the project is slated to attend the inauguration on Monday. Tron also sponsored the industry's inaugural gala, the \"crypto ball\" on Friday night in Washington, D.C, a source told CoinDesk.\n\nTrump's team didn't immediately respond to a request for comment, and neither did World Liberty Financial.",
    "url": "https://www.coindesk.com/business/2025/01/18/trump-backed-world-liberty-financial-to-acquire-trx-for-its-treasury-source",
    "llm_analysis": {
        "entities": {
            "persons": [
                "Donald Trump",
                "Justin Sun"
            ],
            "positions": [
                "U.S. President-elect",
                "chief crypto advocate",
                "founder",
                "advisor",
                "single-largest holder"
            ],
            "companies": [
                "World Liberty Financial",
                "Tron"
            ],
            "organizations": [
                "White House",
                "CoinDesk"
            ]
        },
        "cryptocurrencies": [
            "TRX",
            "WLFI",
            "AAVE",
            "LINK"
        ],
        "impact_sentiment": "Bullish",
        "reasoning": "The news describes Trump-backed World Liberty Financial acquiring TRX for its treasury and Trump's return to the White House being heralded as a watershed moment for the crypto industry, indicating positive market confidence."
    }
}