{
    "title": "KBW Starts Strategy Coverage With Outperform, Says Firm Offers Leveraged Bitcoin Exposure",
    "time": "2025-02-07T13:46:00",
    "author": "Will Canny",
    "summary": "The stock could be eligible for S&P 500 index inclusion once it adopts updated FASB accounting standards, the report said.",
    "content": "Strategy (MSTR), the company formerly known as MicroStrategy, is an appealing investment for equity investors looking for levered bitcoin\nBTC\n$104,093.36\nexposure, investment bank KBW said in a research report Thursday.\n\nKBW assumed coverage of Strategy with an outperform rating and a $560 price target. The shares were 1% higher at around $329 in early trading.\n\nOnce Strategy, the company co-founded by Michael Saylor, adopts the Financial Accounting Standards Board (FASB) updated accounting treatment for bitcoin holdings in the first quarter of this year, it will shift from an \"outdated measurement approach to fair value accounting, with unrealized gains/losses flowing to net income,\" analyst Bill Papanastasiou wrote.\n\nThe company reported an impairment loss of $1 billion for the fourth quarter of 2024 because it did not adopt new FASB rules.\n\nOne of the most important criteria for joining the S&P 500 index is positive net earnings in the last quarter and the sum of the previous four quarters, the report said.\n\nStrategy has the \"largest bitcoin treasury held by a public operating company,\" , and the company has a number of tools it could use to expand its BTC stack, KBW said.\n\nIn the longer term, there is also the opportunity for Strategy to generate yield on-chain from applications built on the Bitcoin network, the bank said.\n\nThe development of applications on top of the Bitcoin network could result in a massive value unlock, as it is the most secure, decentralized and valuable public blockchain, the report added.\n\nRead more: Strategy Sees Thursday Nasdaq Listing for STRK Convertible Preferred Stock",
    "url": "https://www.coindesk.com/markets/2025/02/07/kbw-starts-strategy-coverage-with-outperform-offers-leveraged-bitcoin-exposure",
    "llm_analysis": {
        "entities": {
            "persons": [
                "Michael Saylor",
                "Bill Papanastasiou"
            ],
            "positions": [
                "analyst"
            ],
            "companies": [
                "Strategy",
                "MicroStrategy",
                "KBW"
            ],
            "organizations": [
                "Financial Accounting Standards Board",
                "FASB",
                "S&P 500"
            ]
        },
        "cryptocurrencies": [
            "Bitcoin",
            "BTC"
        ],
        "impact_sentiment": "Bullish",
        "reasoning": "The news describes Strategy as an appealing investment for leveraged bitcoin exposure with positive analyst coverage and potential S&P 500 inclusion, indicating market confidence and positive sentiment toward bitcoin."
    }
}