{
    "title": "Trump-Backed World Liberty Financial Snaps Up $21.5M in WBTC, ETH, MOVE",
    "time": "2025-03-06T07:26:00",
    "author": "Shaurya Malwa",
    "summary": "The WLFI purchases come days ahead of a White House Crypto Summit scheduled on Mar. 7.",
    "content": "World Liberty Financial (WLFI), the decentralized finance (DeFi) venture tied to U.S. President Donald Trump and his family, added over $21.5 million worth of ether (ETH), wrapped bitcoin (WBTC), and MOVE tokens to its treasury on Wednesday, data shows.\n\nWLFI acquired 4,468 ETH at roughly $2,238 each (totaling $10 million), 110.6 WBTC at $90,415 (another $10 million), and 3.42 million MOVE tokens at $0.438 apiece ($1.5 million).\n\nThe WLFI purchases, where Trump and his sons hold ambassadorial roles, come days ahead of a White House Crypto Summit scheduled on Mar. 7, where the President is set to meet with several high-profile crypto founders.\n\nWorld Liberty Financial (WLFI), the decentralized finance (DeFi) venture tied to U.S. President Donald Trump and his family, added over $21.5 million worth of ether (ETH), wrapped bitcoin (WBTC), and MOVE tokens to its treasury on Wednesday, data shows.\n\nWLFI acquired 4,468 ETH at roughly $2,238 each (totaling $10 million), 110.6 WBTC at $90,415 (another $10 million), and 3.42 million MOVE tokens at $0.438 apiece ($1.5 million).\n\nThe WLFI purchases, where Trump and his sons hold ambassadorial roles, come days ahead of a White House Crypto Summit scheduled on Mar. 7, where the President is set to meet with several high-profile crypto founders.\n\nMore For You\n\nOwlTing: Stablecoin Infrastructure for the Future\n\nStablecoin payment volumes have grown to $19.4B year-to-date in 2025. OwlTing aims to capture this market by developing payment infrastructure that processes transactions in seconds for fractions of a cent.\n\nBitcoin Nears Lowest Since June as U.S. Government Shutdown Hits Joint Longest\n\nThe bitcoin price is approaching $103,000 as the federal shutdown ties the 2018â€“2019 record while dollar the strengthens and tech market futures decline.\n\nWhat to know:",
    "url": "https://www.coindesk.com/markets/2025/03/06/trump-backed-world-liberty-financial-snaps-up-usd21-5m-in-wbtc-eth-move",
    "llm_analysis": {
        "entities": {
            "persons": [
                "Donald Trump",
                "Trump",
                "President"
            ],
            "positions": [
                "U.S. President",
                "ambassadorial roles"
            ],
            "companies": [
                "World Liberty Financial",
                "WLFI",
                "OwlTing"
            ],
            "organizations": [
                "White House"
            ]
        },
        "cryptocurrencies": [
            "ETH",
            "WBTC",
            "MOVE",
            "Bitcoin",
            "BTC"
        ],
        "impact_sentiment": "Bullish",
        "reasoning": "The news describes significant institutional buying of $21.5M in cryptocurrencies by a Trump-backed venture ahead of a White House Crypto Summit, indicating market confidence and positive momentum."
    }
}